<?xml version="1.0" encoding="UTF-8"?>

<jar-versions>
  <jar name="FastInfoset.jar" specVersion="1.0" specVendor="JBoss (http://www.jboss.org/)" specTitle="ITU-T Rec. X.891 | ISO/IEC 24824-1 (Fast Infoset)" implVersion="1.2.2" implVendor="Sun Microsystems, Inc." implTitle="Fast Infoset Implementation " implVendorID="com.sun" implURL="http://www.jboss.org/" sealed="false" md5Digest="218d90293470fb04258bee0836bfe1c5"/>
  <jar name="activation.jar" specVersion="1.1" specVendor="Sun Microsystems, Inc." specTitle="JavaBeans(TM) Activation Framework Specification" implVersion="1.1" implVendor="Sun Microsystems, Inc." implTitle="Sun Java System Application Server" implVendorID="com.sun" implURL="http://www.jboss.org/" sealed="false" md5Digest="2a97042e3cbf2d62c0005f17adbe3918"/>
  <jar name="antlr.jar" specVersion="5.0.0.GA" specVendor="JBoss (http://www.jboss.org/)" specTitle="JBoss" implVersion="5.0.0.GA (build: SVNTag=JBoss_5_0_0_GA date=200812041714)" implVendor="JBoss Inc." implTitle="JBoss [Morpheus]" implVendorID="http://www.jboss.org/" implURL="http://www.jboss.org/" sealed="false" md5Digest="783b0432f25ce5990c708087c5f33fd"/>
  <jar name="applet.jar" specVersion="5.0.0.GA" specVendor="JBoss (http://www.jboss.org/)" specTitle="JBoss" implVersion="5.0.0.GA (build: SVNTag=JBoss_5_0_0_GA date=200812041714)" implVendor="JBoss Inc." implTitle="JBoss [Morpheus]" implVendorID="http://www.jboss.org/" implURL="http://www.jboss.org/" sealed="false" md5Digest="5f5d5f925dd5f43399f9a78b2b4c9169"/>
  <jar name="autonumber-plugin.jar" specVersion="5.0.0.GA" specVendor="JBoss (http://www.jboss.org/)" specTitle="JBoss" implVersion="5.0.0.GA (build: SVNTag=JBoss_5_0_0_GA date=200812041714)" implVendor="JBoss Inc." implTitle="JBoss [Morpheus]" implVendorID="http://www.jboss.org/" implURL="http://www.jboss.org/" sealed="false" md5Digest="e8aab912f33049e3429031178d0133cc"/>
  <jar name="avalon-framework.jar" specVersion="1.0" specVendor="Apache Software Foundation" specTitle="Avalon Framework API" implVersion="4.1.5" implVendor="Apache Software Foundation" implTitle="JBoss [Morpheus]" implVendorID="ASF" implURL="http://www.jboss.org/" sealed="false" md5Digest="5956ad904c4eccdd677ebff5305319d6"/>
  <jar name="bcel.jar" specVersion="5.0.0.GA" specVendor="JBoss (http://www.jboss.org/)" specTitle="JBoss" implVersion="5.0.0.GA (build: SVNTag=JBoss_5_0_0_GA date=200812041714)" implVendor="JBoss Inc." implTitle="JBoss [Morpheus]" implVendorID="http://www.jboss.org/" implURL="http://www.jboss.org/" sealed="false" md5Digest="cccd7d310f2c02a7c50504fac6b8a2b3"/>
  <jar name="bsf.jar" specVersion="5.0.0.GA" specVendor="JBoss (http://www.jboss.org/)" specTitle="JBoss" implVersion="5.0.0.GA (build: SVNTag=JBoss_5_0_0_GA date=200812041714)" implVendor="JBoss Inc." implTitle="JBoss [Morpheus]" implVendorID="http://www.jboss.org/" implURL="http://www.jboss.org/" sealed="false" md5Digest="82466f8f9c71d6005d467290bab2e6d5"/>
  <jar name="bsh-deployer.jar" specVersion="5.0.0.GA" specVendor="JBoss (http://www.jboss.org/)" specTitle="JBoss" implVersion="5.0.0.GA (build: SVNTag=JBoss_5_0_0_GA date=200812041714)" implVendor="JBoss Inc." implTitle="JBoss [Morpheus]" implVendorID="http://www.jboss.org/" implURL="http://www.jboss.org/" sealed="false" md5Digest="1f64b0ae0891a27c35d5c5b5542241d0"/>
  <jar name="bsh.jar" specVersion="5.0.0.GA" specVendor="JBoss (http://www.jboss.org/)" specTitle="JBoss" implVersion="5.0.0.GA (build: SVNTag=JBoss_5_0_0_GA date=200812041714)" implVendor="JBoss Inc." implTitle="JBoss [Morpheus]" implVendorID="http://www.jboss.org/" implURL="http://www.jboss.org/" sealed="false" md5Digest="d3742ef82be6927e4293a8dd4df99542"/>
  <jar name="commons-collections.jar" specVersion="3.1" specVendor="Apache Software Foundation" specTitle="Commons Collections" implVersion="3.1" implVendor="Apache Software Foundation" implTitle="JBoss [Morpheus]" implVendorID="" implURL="http://www.jboss.org/" sealed="false" md5Digest="850d41ea2f9ee152b67b0424d99a80de"/>
  <jar name="commons-httpclient.jar" specVersion="5.0.0.GA" specVendor="Apache Software Foundation" specTitle="Jakarta Commons HttpClient" implVersion="3.0" implVendor="Apache Software Foundation" implTitle="org.apache.commons.httpclient" implVendorID="http://www.jboss.org/" implURL="http://www.jboss.org/" sealed="false" md5Digest="4c7029715fb5974fc8a3ccf148d1d234"/>
  <jar name="commons-logging.jar" specVersion="1.0" specVendor="Apache Software Foundation" specTitle="Jakarta Commons Logging" implVersion="1.1.0.jboss" implVendor="Red Hat Middleware LLC" implTitle="Jakarta Commons Logging" implVendorID="jboss.org" implURL="http://www.jboss.org/" sealed="false" md5Digest="c4b041fbe11fecf052cdd7fbff67407"/>
  <jar name="concurrent.jar" specVersion="5.0.0.GA" specVendor="JBoss (http://www.jboss.org/)" specTitle="JBoss" implVersion="5.0.0.GA (build: SVNTag=JBoss_5_0_0_GA date=200812041714)" implVendor="JBoss Inc." implTitle="JBoss [Morpheus]" implVendorID="http://www.jboss.org/" implURL="http://www.jboss.org/" sealed="false" md5Digest="2dee7c6659145e6572c930d1bc66bb89"/>
  <jar name="console-mgr-classes.jar" specVersion="5.0.0.GA" specVendor="JBoss (http://www.jboss.org/)" specTitle="JBoss" implVersion="5.0.0.GA (build: SVNTag=JBoss_5_0_0_GA date=200812041714)" implVendor="JBoss Inc." implTitle="JBoss [Morpheus]" implVendorID="http://www.jboss.org/" implURL="http://www.jboss.org/" sealed="false" md5Digest="4a4c1950f146061fc9a8f34a860b589b"/>
  <jar name="deployment-service.sar" specVersion="5.0.0.GA" specVendor="JBoss (http://www.jboss.org/)" specTitle="JBoss" implVersion="5.0.0.GA (build: SVNTag=JBoss_5_0_0_GA date=200812041714)" implVendor="JBoss Inc." implTitle="JBoss [Morpheus]" implVendorID="http://www.jboss.org/" implURL="http://www.jboss.org/" sealed="false" md5Digest="ed1b5d940b5c739c6bead074eeb1f372"/>
  <jar name="derby-plugin.jar" specVersion="5.0.0.GA" specVendor="JBoss (http://www.jboss.org/)" specTitle="JBoss" implVersion="5.0.0.GA (build: SVNTag=JBoss_5_0_0_GA date=200812041714)" implVendor="JBoss Inc." implTitle="JBoss [Morpheus]" implVendorID="http://www.jboss.org/" implURL="http://www.jboss.org/" sealed="false" md5Digest="3f7856c2f5da2a69916de48c69252807"/>
  <jar name="dom4j.jar" specVersion="5.0.0.GA" specVendor="MetaStuff Ltd." specTitle="dom4j : XML framework for Java" implVersion="1.6.1" implVendor="MetaStuff Ltd." implTitle="org.dom4j" implVendorID="http://www.jboss.org/" implURL="http://www.jboss.org/" sealed="false" md5Digest="f1fbe828e399a58254fe0b30f987a546"/>
  <jar name="dtdparser121.jar" specVersion="5.0.0.GA" specVendor="JBoss (http://www.jboss.org/)" specTitle="JBoss" implVersion="5.0.0.GA (build: SVNTag=JBoss_5_0_0_GA date=200812041714)" implVendor="JBoss Inc." implTitle="JBoss [Morpheus]" implVendorID="http://www.jboss.org/" implURL="http://www.jboss.org/" sealed="false" md5Digest="dde04367dbbd3a777e2a88f975919b42"/>
  <jar name="ejb-management.jar" specVersion="5.0.0.GA" specVendor="JBoss (http://www.jboss.org/)" specTitle="JBoss" implVersion="5.0.0.GA (build: SVNTag=JBoss_5_0_0_GA date=200812041714)" implVendor="JBoss Inc." implTitle="JBoss [Morpheus]" implVendorID="http://www.jboss.org/" implURL="http://www.jboss.org/" sealed="false" md5Digest="6f2bc79b7063d5cd827541a1497f42b2"/>
  <jar name="ejb3-persistence.jar" specVersion="3.0 Final Release (1.0.2.GA)" specVendor="Sun Microsystems, Inc." specTitle="EJB 3.0" implVersion="3.0 Final Release (1.0.2.GA) April 2 2008" implVendor="hibernate.org" implTitle="EJB" implVendorID="http://www.jboss.org/" implURL="http://www.jboss.org/" sealed="false" md5Digest="ca6e9c58467018d60791c0ee982f1a5e"/>
  <jar name="el-api.jar" specVersion="5.0.0.GA" specVendor="JBoss (http://www.jboss.org/)" specTitle="JBoss" implVersion="5.0.0.GA (build: SVNTag=JBoss_5_0_0_GA date=200812041714)" implVendor="JBoss Inc." implTitle="JBoss [Morpheus]" implVendorID="http://www.jboss.org/" implURL="http://www.jboss.org/" sealed="false" md5Digest="fd2089134d4378af80b16052c8f6ac3a"/>
  <jar name="getopt.jar" specVersion="5.0.0.GA" specVendor="JBoss (http://www.jboss.org/)" specTitle="JBoss" implVersion="5.0.0.GA (build: SVNTag=JBoss_5_0_0_GA date=200812041714)" implVendor="JBoss Inc." implTitle="JBoss [Morpheus]" implVendorID="http://www.jboss.org/" implURL="http://www.jboss.org/" sealed="false" md5Digest="88e99395c67b9d2315aee8235a88b443"/>
  <jar name="hibernate-annotations.jar" specVersion="1.0" specVendor="jcp.org" specTitle="Java Persistence" implVersion="3.4.0.GA" implVendor="hibernate.org" implTitle="Hibernate Annotations" implVendorID="hibernate.org" implURL="http://annotations.hibernate.org" sealed="false" md5Digest="f3acaec379ce18610268123491cb31ae"/>
  <jar name="hibernate-commons-annotations.jar" specVersion="5.0.0.GA" specVendor="JBoss (http://www.jboss.org/)" specTitle="JBoss" implVersion="3.1.0.GA" implVendor="hibernate.org" implTitle="Hibernate Commons Annotations" implVendorID="hibernate.org" implURL="http://annotations.hibernate.org" sealed="false" md5Digest="761a254eafb8cd4c092b527a5c09dfb6"/>
  <jar name="hibernate-core.jar" specVersion="3.3.1.GA" specVendor="Hibernate.org" specTitle="Hibernate Core" implVersion="3.3.1.GA" implVendor="Hibernate.org" implTitle="Hibernate Core" implVendorID="org.hibernate" implURL="http://hibernate.org/hibernate-core" sealed="false" md5Digest="edff214e26a4f95270b491f10db2164f"/>
  <jar name="hibernate-entitymanager.jar" specVersion="1.0" specVendor="jcp.org" specTitle="Java Persistence" implVersion="3.4.0.GA" implVendor="hibernate.org" implTitle="Hibernate EntityManager" implVendorID="hibernate.org" implURL="http://entitymanager.hibernate.org" sealed="false" md5Digest="6c94577b5af0913875676eddfee546db"/>
  <jar name="hibernate-jbosscache2.jar" specVersion="3.3.1.GA" specVendor="Hibernate.org" specTitle="Hibernate JBossCache2.x Integration" implVersion="3.3.1.GA" implVendor="Hibernate.org" implTitle="Hibernate JBossCache2.x Integration" implVendorID="org.hibernate" implURL="http://hibernate.org/hibernate-jbosscache2" sealed="false" md5Digest="7266fd2d98fa3dff76b56bb38dc8a9ce"/>
  <jar name="hibernate-jmx.jar" specVersion="3.3.1.GA" specVendor="Hibernate.org" specTitle="Hibernate JMX Module" implVersion="3.3.1.GA" implVendor="Hibernate.org" implTitle="Hibernate JMX Module" implVendorID="org.hibernate" implURL="http://hibernate.org/hibernate-jmx" sealed="false" md5Digest="1e336125128fbee9abb555cbbec28ec5"/>
  <jar name="hibernate-validator.jar" specVersion="5.0.0.GA" specVendor="JBoss (http://www.jboss.org/)" specTitle="JBoss" implVersion="3.1.0.GA" implVendor="hibernate.org" implTitle="Hibernate Validator" implVendorID="hibernate.org" implURL="http://validator.hibernate.org" sealed="false" md5Digest="d830aac57ef2e710a1de9f81725e5768"/>
  <jar name="hsqldb-plugin.jar" specVersion="5.0.0.GA" specVendor="JBoss (http://www.jboss.org/)" specTitle="JBoss" implVersion="5.0.0.GA (build: SVNTag=JBoss_5_0_0_GA date=200812041714)" implVendor="JBoss Inc." implTitle="JBoss [Morpheus]" implVendorID="http://www.jboss.org/" implURL="http://www.jboss.org/" sealed="false" md5Digest="480572bfbd868fa83831c1767d02773"/>
  <jar name="hsqldb.jar" specVersion="5.0.0.GA" specVendor="JBoss (http://www.jboss.org/)" specTitle="JBoss" implVersion="5.0.0.GA (build: SVNTag=JBoss_5_0_0_GA date=200812041714)" implVendor="JBoss Inc." implTitle="JBoss [Morpheus]" implVendorID="http://www.jboss.org/" implURL="http://www.jboss.org/" sealed="false" md5Digest="a948e2171c88b9692d9b3d594de0688a"/>
  <jar name="jacorb.jar" specVersion="5.0.0.GA" specVendor="JBoss (http://www.jboss.org/)" specTitle="JBoss" implVersion="5.0.0.GA (build: SVNTag=JBoss_5_0_0_GA date=200812041714)" implVendor="JBoss Inc." implTitle="JBoss [Morpheus]" implVendorID="http://www.jboss.org/" implURL="http://www.jboss.org/" sealed="false" md5Digest="f0c39344b7663c86baee76c1f350f822"/>
  <jar name="jasper-jdt.jar" specVersion="5.0.0.GA" specVendor="JBoss (http://www.jboss.org/)" specTitle="JBoss" implVersion="5.0.0.GA (build: SVNTag=JBoss_5_0_0_GA date=200812041714)" implVendor="JBoss Inc." implTitle="JBoss [Morpheus]" implVendorID="http://www.jboss.org/" implURL="http://www.jboss.org/" sealed="false" md5Digest="4956513b72f7648baabac32b2e3f827c"/>
  <jar name="javassist.jar" specVersion="3.9.0.GA" specVendor="Shigeru Chiba, Tokyo Institute of Technology" specTitle="Javassist" implVersion="5.0.0.GA (build: SVNTag=JBoss_5_0_0_GA date=200812041714)" implVendor="JBoss Inc." implTitle="JBoss [Morpheus]" implVendorID="http://www.jboss.org/" implURL="http://www.jboss.org/" sealed="false" md5Digest="38d67f4072f3428843f6d2cf962f7fbd"/>
  <jar name="jaxb-api.jar" specVersion="2.1" specVendor="Sun Microsystems, Inc." specTitle="Java Architecture for XML Binding" implVersion="5.0.0.GA (build: SVNTag=JBoss_5_0_0_GA date=200812041714)" implVendor="JBoss Inc." implTitle="JBoss [Morpheus]" implVendorID="http://www.jboss.org/" implURL="http://www.jboss.org/" sealed="false" md5Digest="d4e54d4a9831c44ad3c911ec6a2b7099"/>
  <jar name="jaxb-impl.jar" specVersion="2.1" specVendor="Sun Microsystems, Inc." specTitle="Java Architecture for XML Binding" implVersion="2.1.9" implVendor="Sun Microsystems, Inc." implTitle="JAXB Reference Implementation " implVendorID="com.sun" implURL="http://www.jboss.org/" sealed="false" md5Digest="75d8ff7b3c19870f8c7c61e13cdd56a6"/>
  <jar name="jaxb-xjc.jar" specVersion="2.1" specVendor="Sun Microsystems, Inc." specTitle="Java Architecture for XML Binding" implVersion="2.1.9" implVendor="Sun Microsystems, Inc." implTitle="JAXB Reference Implementation " implVendorID="com.sun" implURL="http://www.jboss.org/" sealed="false" md5Digest="ee2efdd881a8f5c8543930205faa539f"/>
  <jar name="jaxen.jar" specVersion="5.0.0.GA" specVendor="Codehaus" specTitle="Universal Java XPath Engine" implVersion="1.1" implVendor="Codehaus" implTitle="org.jaxen" implVendorID="http://www.jboss.org/" implURL="http://www.jboss.org/" sealed="false" md5Digest="777706a51355e14c2bdaa441a8aa4df1"/>
  <jar name="jaxws-rt.jar" specVersion="2.0" specVendor="JBoss (http://www.jboss.org/)" specTitle="The Java API for XML Web Services" implVersion="2.0" implVendor="Sun Microsystems Inc" implTitle="JAX-WS Implementation" implVendorID="com.sun" implURL="http://www.jboss.org/" sealed="false" md5Digest="d60c2ddcb3b5bbb6a7ddccba0f932b7a"/>
  <jar name="jaxws-tools.jar" specVersion="2.0" specVendor="JBoss (http://www.jboss.org/)" specTitle="The Java API for XML Web Services" implVersion="2.0" implVendor="Sun Microsystems Inc" implTitle="JAX-WS Implementation" implVendorID="com.sun" implURL="http://www.jboss.org/" sealed="false" md5Digest="b19a4a4d9cb474a877ae50cc8c24d92"/>
  <jar name="jboss-aop-asintegration-core.jar" specVersion="2.0.0.SP1" specVendor="JBoss, a division of Red Hat, Inc." specTitle="JBoss AOP AS Integration Core" implVersion="2.0.0.SP1" implVendor="JBoss, a division of Red Hat, Inc." implTitle="JBoss AOP AS Integration Core" implVendorID="org.jboss.aop" implURL="http://www.jboss.org/jbossaop/jboss-aop-asintegration-core" sealed="false" md5Digest="7594b71cecf913eee3a0f743401b0cac"/>
  <jar name="jboss-aop-asintegration-jmx.jar" specVersion="2.0.0.SP1" specVendor="JBoss, a division of Red Hat, Inc." specTitle="JBoss AOP AS Integration JMX" implVersion="2.0.0.SP1" implVendor="JBoss, a division of Red Hat, Inc." implTitle="JBoss AOP AS Integration JMX" implVendorID="org.jboss.aop" implURL="http://www.jboss.org/jbossaop/jboss-aop-asintegration-jmx" sealed="false" md5Digest="781011c82125fd20b1a74fbb3071e31c"/>
  <jar name="jboss-aop-asintegration-mc.jar" specVersion="2.0.0.SP1" specVendor="JBoss, a division of Red Hat, Inc." specTitle="JBoss AOP AS Integration MC" implVersion="2.0.0.SP1" implVendor="JBoss, a division of Red Hat, Inc." implTitle="JBoss AOP AS Integration MC" implVendorID="org.jboss.aop" implURL="http://www.jboss.org/jbossaop/jboss-aop-asintegration-mc" sealed="false" md5Digest="9e4597adb7168e031771d5e59a51da86"/>
  <jar name="jboss-aop-aspects.jar" specVersion="2.0.0.SP1" specVendor="JBoss, a division of Red Hat, Inc." specTitle="JBoss AOP Aspects" implVersion="2.0.0.SP1" implVendor="JBoss, a division of Red Hat, Inc." implTitle="JBoss AOP Aspects" implVendorID="org.jboss.aop" implURL="http://www.jboss.org/jbossaop/jboss-aop-aspects" sealed="false" md5Digest="9474820e2e7ff44e58e77b7020fc0b0e"/>
  <jar name="jboss-aop-client.jar" specVersion="2.0.0.SP1" specVendor="JBoss, a division of Red Hat, Inc." specTitle="JBoss AOP Framework" implVersion="2.0.0.SP1" implVendor="JBoss, a division of Red Hat, Inc." implTitle="JBoss AOP Framework" implVendorID="org.jboss.aop" implURL="http://www.jboss.org/jbossaop" sealed="false" md5Digest="5407dc87e7fde6ccad878907a16b44c"/>
  <jar name="jboss-aop-jboss5.jar" specVersion="jboss-aspect-library-1.3" specVendor="JBoss (http://www.jboss.org/)" specTitle="JBoss AOP Aspect Library" implVersion="jboss-aspect-library-1.3" implVendor="JBoss Inc." implTitle="JBoss AOP Aspect Library" implVendorID="http://www.jboss.org/" implURL="http://www.jboss.org/" sealed="false" md5Digest="1727029d38d5898de38a7bb305cfd93b"/>
  <jar name="jboss-aop-mc-int.jar" specVersion="2.0.2.GA" specVendor="JBoss, a division of Red Hat, Inc." specTitle="JBoss Microcontainer AOP MC INT" implVersion="2.0.2.GA" implVendor="JBoss, a division of Red Hat, Inc." implTitle="JBoss Microcontainer AOP MC INT" implVendorID="org.jboss.microcontainer" implURL="http://www.jboss.com/products/jbossmc" sealed="false" md5Digest="e8540c9a1ba4a9a7d336f18f274ee72e"/>
  <jar name="jboss-aop.jar" specVersion="2.0.0.SP1" specVendor="JBoss, a division of Red Hat, Inc." specTitle="JBoss AOP Framework" implVersion="2.0.0.SP1" implVendor="JBoss, a division of Red Hat, Inc." implTitle="JBoss AOP Framework" implVendorID="org.jboss.aop" implURL="http://www.jboss.org/jbossaop" sealed="false" md5Digest="a7e59c0aedf9e2072b5d5b61fd92ef4c"/>
  <jar name="jboss-appclient.jar" specVersion="JBoss EJB 3.0 RC7 - FD" specVendor="JBoss" specTitle="JBoss EJB 3.0" implVersion="JBoss EJB 3.0 RC7 - FD" implVendor="JBoss" implTitle="JBoss EJB 3.0" implVendorID="http://www.jboss.org/" implURL="http://www.jboss.com/products/ejb3" sealed="false" md5Digest="5ae33acc765db9882aa1f42968fab8ae"/>
  <jar name="jboss-aspect-jdk50-client.jar" specVersion="jboss-aspect-library-1.3" specVendor="JBoss (http://www.jboss.org/)" specTitle="JBoss AOP Aspect Library" implVersion="jboss-aspect-library-1.3" implVendor="JBoss Inc." implTitle="JBoss AOP Aspect Library" implVendorID="http://www.jboss.org/" implURL="http://www.jboss.org/" sealed="false" md5Digest="8c43845410077ecc83f67546eb0b6919"/>
  <jar name="jboss-aspect-library.jar" specVersion="jboss-aspect-library-1.3" specVendor="JBoss (http://www.jboss.org/)" specTitle="JBoss AOP Aspect Library" implVersion="jboss-aspect-library-1.3" implVendor="JBoss Inc." implTitle="JBoss AOP Aspect Library" implVendorID="http://www.jboss.org/" implURL="http://www.jboss.org/" sealed="false" md5Digest="e2466e3d548e1ce9e023f7fa1ae89d02"/>
  <jar name="jboss-bindingservice.jar" specVersion="5.0.0.GA" specVendor="JBoss (http://www.jboss.org/)" specTitle="JBoss" implVersion="5.0.0.GA (build: SVNTag=JBoss_5_0_0_GA date=200812041714)" implVendor="JBoss Inc." implTitle="JBoss [Morpheus]" implVendorID="http://www.jboss.org/" implURL="http://www.jboss.org/" sealed="false" md5Digest="9046a9e5fd3126241ff4be317b2acd0c"/>
  <jar name="jboss-bootstrap.jar" specVersion="5.0.0.GA" specVendor="JBoss (http://www.jboss.org/)" specTitle="JBoss" implVersion="5.0.0.GA (build: SVNTag=JBoss_5_0_0_GA date=200812041714)" implVendor="JBoss Inc." implTitle="JBoss [Morpheus]" implVendorID="http://www.jboss.org/" implURL="http://www.jboss.org/" sealed="false" md5Digest="1e7f1f35904f3f5cab2d46492f994aee"/>
  <jar name="jboss-classloader.jar" specVersion="2.0.1.GA" specVendor="JBoss, a division of Red Hat, Inc." specTitle="JBoss ClassLoader" implVersion="2.0.1.GA" implVendor="JBoss, a division of Red Hat, Inc." implTitle="JBoss ClassLoader" implVendorID="org.jboss.cl" implURL="http://www.jboss.com/products/jbossmc" sealed="false" md5Digest="5e6efb46df3d242bd4bfc7ad974c681e"/>
  <jar name="jboss-classloading-spi.jar" specVersion="5.0.3.GA" specVendor="JBoss, a division of Red Hat, Inc." specTitle="JBoss ClassLoading 5.0.0 SPI" implVersion="5.0.3.GA" implVendor="JBoss, a division of Red Hat, Inc." implTitle="JBoss ClassLoading 5.0.0 SPI" implVendorID="org.jboss.integration" implURL="http://www.jboss.org" sealed="false" md5Digest="33a1060c711a48bd00cdea3b1f0559ea"/>
  <jar name="jboss-classloading-vfs.jar" specVersion="2.0.1.GA" specVendor="JBoss, a division of Red Hat, Inc." specTitle="JBoss ClassLoading VFS" implVersion="2.0.1.GA" implVendor="JBoss, a division of Red Hat, Inc." implTitle="JBoss ClassLoading VFS" implVendorID="org.jboss.cl" implURL="http://www.jboss.com/products/jbossmc" sealed="false" md5Digest="26f5ee478956774205883b59e14b3f2d"/>
  <jar name="jboss-classloading.jar" specVersion="2.0.1.GA" specVendor="JBoss, a division of Red Hat, Inc." specTitle="JBoss ClassLoading" implVersion="2.0.1.GA" implVendor="JBoss, a division of Red Hat, Inc." implTitle="JBoss ClassLoading" implVendorID="org.jboss.cl" implURL="http://www.jboss.com/products/jbossmc" sealed="false" md5Digest="b1d167fdb61ce004e0652b91338af386"/>
  <jar name="jboss-client.jar" specVersion="5.0.0.GA" specVendor="JBoss (http://www.jboss.org/)" specTitle="JBoss" implVersion="5.0.0.GA (build: SVNTag=JBoss_5_0_0_GA date=200812041714)" implVendor="JBoss Inc." implTitle="JBoss [Morpheus]" implVendorID="http://www.jboss.org/" implURL="http://www.jboss.org/" sealed="false" md5Digest="d895720b47c19a79c607a0c57a7f55f0"/>
  <jar name="jboss-common-core.jar" specVersion="2.2.10.GA" specVendor="JBoss, a division of Red Hat, Inc." specTitle="JBoss Common Classes" implVersion="2.2.10.GA" implVendor="JBoss, a division of Red Hat, Inc." implTitle="JBoss Common Classes" implVendorID="org.jboss" implURL="http://www.jboss.org" sealed="false" md5Digest="1b582b374fd2d76ae59495801c0c75ad"/>
  <jar name="jboss-common-jdbc-wrapper.jar" specVersion="5.0.0.GA" specVendor="JBoss (http://www.jboss.org/)" specTitle="JBoss" implVersion="5.0.0.GA (build: SVNTag=JBoss_5_0_0_GA date=200812041714)" implVendor="JBoss Inc." implTitle="JBoss [Morpheus]" implVendorID="http://www.jboss.org/" implURL="http://www.jboss.org/" sealed="false" md5Digest="4f024375cec731dc2bb54697796b1497"/>
  <jar name="jboss-current-invocation-aspects.jar" specVersion="1.0.0.GA" specVendor="JBoss Inc." specTitle="JBoss Current Invocation Aspects" implVersion="1.0.0.GA" implVendor="JBoss Inc." implTitle="JBoss Current Invocation Aspects" implVendorID="org.jboss.aspects" implURL="http://www.jboss.org/jbossas" sealed="false" md5Digest="a60396e1b02b5f2fc69504ff13211a60"/>
  <jar name="jboss-dependency.jar" specVersion="2.0.2.GA" specVendor="JBoss, a division of Red Hat, Inc." specTitle="JBoss Microcontainer Dependency" implVersion="2.0.2.GA" implVendor="JBoss, a division of Red Hat, Inc." implTitle="JBoss Microcontainer Dependency" implVendorID="org.jboss.microcontainer" implURL="http://www.jboss.com/products/jbossmc" sealed="false" md5Digest="1b5e3208e63edee720c71c81167d4dd6"/>
  <jar name="jboss-deployers-client-spi.jar" specVersion="2.0.3.GA" specVendor="JBoss, a division of Red Hat, Inc." specTitle="JBoss Deployers Client SPI" implVersion="2.0.3.GA" implVendor="JBoss, a division of Red Hat, Inc." implTitle="JBoss Deployers Client SPI" implVendorID="org.jboss.deployers" implURL="http://www.jboss.com/products/jbossmc" sealed="false" md5Digest="b004774dc6ff26e775a1bbf2f651f2b"/>
  <jar name="jboss-deployers-client.jar" specVersion="2.0.3.GA" specVendor="JBoss, a division of Red Hat, Inc." specTitle="JBoss Deployers Client" implVersion="2.0.3.GA" implVendor="JBoss, a division of Red Hat, Inc." implTitle="JBoss Deployers Client" implVendorID="org.jboss.deployers" implURL="http://www.jboss.com/products/jbossmc" sealed="false" md5Digest="da2506beba58aa3550aa0a87b048f3dc"/>
  <jar name="jboss-deployers-core-spi.jar" specVersion="2.0.3.GA" specVendor="JBoss, a division of Red Hat, Inc." specTitle="JBoss Deployers Core SPI" implVersion="2.0.3.GA" implVendor="JBoss, a division of Red Hat, Inc." implTitle="JBoss Deployers Core SPI" implVendorID="org.jboss.deployers" implURL="http://www.jboss.com/products/jbossmc" sealed="false" md5Digest="8c38591f1971c0b995057b84c62b340e"/>
  <jar name="jboss-deployers-core.jar" specVersion="2.0.3.GA" specVendor="JBoss, a division of Red Hat, Inc." specTitle="JBoss Deployers Core" implVersion="2.0.3.GA" implVendor="JBoss, a division of Red Hat, Inc." implTitle="JBoss Deployers Core" implVendorID="org.jboss.deployers" implURL="http://www.jboss.com/products/jbossmc" sealed="false" md5Digest="9ca637696a4e42d99aa98b7d0ea74676"/>
  <jar name="jboss-deployers-impl.jar" specVersion="2.0.3.GA" specVendor="JBoss, a division of Red Hat, Inc." specTitle="JBoss Deployers Impl" implVersion="2.0.3.GA" implVendor="JBoss, a division of Red Hat, Inc." implTitle="JBoss Deployers Impl" implVendorID="org.jboss.deployers" implURL="http://www.jboss.com/products/jbossmc" sealed="false" md5Digest="9cdbd93efa108bc7d3de45d91d1caef3"/>
  <jar name="jboss-deployers-spi.jar" specVersion="2.0.3.GA" specVendor="JBoss, a division of Red Hat, Inc." specTitle="JBoss Deployers SPI" implVersion="2.0.3.GA" implVendor="JBoss, a division of Red Hat, Inc." implTitle="JBoss Deployers SPI" implVendorID="org.jboss.deployers" implURL="http://www.jboss.com/products/jbossmc" sealed="false" md5Digest="274209157523cb6ebe0c23f25c3b47dd"/>
  <jar name="jboss-deployers-structure-spi.jar" specVersion="2.0.3.GA" specVendor="JBoss, a division of Red Hat, Inc." specTitle="JBoss Deployers Structure SPI" implVersion="2.0.3.GA" implVendor="JBoss, a division of Red Hat, Inc." implTitle="JBoss Deployers Structure SPI" implVendorID="org.jboss.deployers" implURL="http://www.jboss.com/products/jbossmc" sealed="false" md5Digest="e74069858cce094cc47bf18bf7efbc87"/>
  <jar name="jboss-deployers-vfs-spi.jar" specVersion="2.0.3.GA" specVendor="JBoss, a division of Red Hat, Inc." specTitle="JBoss Deployers VFS SPI" implVersion="2.0.3.GA" implVendor="JBoss, a division of Red Hat, Inc." implTitle="JBoss Deployers VFS SPI" implVendorID="org.jboss.deployers" implURL="http://www.jboss.com/products/jbossmc" sealed="false" md5Digest="89abb7516fb73a14e30d9b3c0b5a6254"/>
  <jar name="jboss-deployers-vfs.jar" specVersion="2.0.3.GA" specVendor="JBoss, a division of Red Hat, Inc." specTitle="JBoss Deployers VFS" implVersion="2.0.3.GA" implVendor="JBoss, a division of Red Hat, Inc." implTitle="JBoss Deployers VFS" implVendorID="org.jboss.deployers" implURL="http://www.jboss.com/products/jbossmc" sealed="false" md5Digest="3613e7d927f90252b30e00ee25467dec"/>
  <jar name="jboss-deployment.jar" specVersion="1.1" specVendor="Sun Microsystems, Inc." specTitle="J2EE Deployment API" implVersion="1.1-DEV" implVendor="JBoss Inc." implTitle="JBoss JSR-88 Deployment API" implVendorID="http://www.jboss.org/" implURL="http://www.jboss.org/" sealed="false" md5Digest="e4bb206ee488aefd46decf0f6e625d19"/>
  <jar name="jboss-ejb3-cache.jar" specVersion="0.13.0" specVendor="JBoss Inc." specTitle="JBoss EJB 3.0 Cache" implVersion="0.13.0" implVendor="JBoss Inc." implTitle="JBoss EJB 3.0 Cache" implVendorID="org.jboss.ejb3" implURL="http://labs.jboss.com/jbossejb3/" sealed="false" md5Digest="a41c8b70a8d32c81c10dbef34bad0fe0"/>
  <jar name="jboss-ejb3-common-client.jar" specVersion="5.0.0.GA" specVendor="JBoss (http://www.jboss.org/)" specTitle="JBoss" implVersion="5.0.0.GA (build: SVNTag=JBoss_5_0_0_GA date=200812041714)" implVendor="JBoss Inc." implTitle="JBoss [Morpheus]" implVendorID="http://www.jboss.org/" implURL="http://www.jboss.org/" sealed="false" md5Digest="db584ac40ce6fef01ecfc6ccb54226a7"/>
  <jar name="jboss-ejb3-common.jar" specVersion="1.0.0-Beta2" specVendor="JBoss Inc." specTitle="JBoss EJB 3.0 Common Utilities" implVersion="1.0.0-Beta2" implVendor="JBoss Inc." implTitle="JBoss EJB 3.0 Common Utilities" implVendorID="org.jboss.ejb3" implURL="http://www.jboss.org/jbossejb3/" sealed="false" md5Digest="d6f5be674e86a27bcde9b121c82ce292"/>
  <jar name="jboss-ejb3-core-client.jar" specVersion="5.0.0.GA" specVendor="JBoss (http://www.jboss.org/)" specTitle="JBoss" implVersion="5.0.0.GA (build: SVNTag=JBoss_5_0_0_GA date=200812041714)" implVendor="JBoss Inc." implTitle="JBoss [Morpheus]" implVendorID="http://www.jboss.org/" implURL="http://www.jboss.org/" sealed="false" md5Digest="3e9d129c40284ec525e1ca6b0053f18a"/>
  <jar name="jboss-ejb3-core.jar" specVersion="1.0.0-Beta10" specVendor="JBoss Inc." specTitle="JBoss EJB 3.0 Core" implVersion="1.0.0-Beta10" implVendor="JBoss Inc." implTitle="JBoss EJB 3.0 Core" implVendorID="org.jboss.ejb3" implURL="http://labs.jboss.com/jbossejb3" sealed="false" md5Digest="689bad53e81a9491fc9aec540a075ef3"/>
  <jar name="jboss-ejb3-deployer.jar" specVersion="JBoss EJB 3.0 RC7 - FD" specVendor="JBoss" specTitle="JBoss EJB 3.0" implVersion="JBoss EJB 3.0 RC7 - FD" implVendor="JBoss" implTitle="JBoss EJB 3.0" implVendorID="http://www.jboss.org/" implURL="http://www.jboss.com/products/ejb3" sealed="false" md5Digest="a349d79526b182dc36104a1d5fa2db17"/>
  <jar name="jboss-ejb3-deployers.jar" specVersion="0.1.2" specVendor="JBoss Inc." specTitle="JBoss EJB3 Deployers" implVersion="0.1.2" implVendor="JBoss Inc." implTitle="JBoss EJB3 Deployers" implVendorID="org.jboss.ejb3" implURL="http://labs.jboss.com/jbossejb3/jboss-ejb3-deployers" sealed="false" md5Digest="1a857adbd2182f4fe5e93debbea3b3a3"/>
  <jar name="jboss-ejb3-ext-api-impl.jar" specVersion="0.4.1" specVendor="JBoss Inc." specTitle="JBoss EJB 3.0 Implementation Classes" implVersion="0.4.1" implVendor="JBoss Inc." implTitle="JBoss EJB 3.0 Implementation Classes" implVendorID="org.jboss.ejb3" implURL="http://labs.jboss.com/jbossejb3/" sealed="false" md5Digest="f926503ef4bf9a550b794b871f07ee03"/>
  <jar name="jboss-ejb3-ext-api.jar" specVersion="0.4" specVendor="JBoss Inc." specTitle="JBoss EJB 3.0 External API" implVersion="0.4" implVendor="JBoss Inc." implTitle="JBoss EJB 3.0 External API" implVendorID="org.jboss.ejb3" implURL="http://labs.jboss.com/jbossejb3/" sealed="false" md5Digest="b830c153785269c553b8941197e4639b"/>
  <jar name="jboss-ejb3-iiop.jar" specVersion="JBoss EJB 3.0 RC7 - FD" specVendor="JBoss" specTitle="JBoss EJB 3.0" implVersion="JBoss EJB 3.0 RC7 - FD" implVendor="JBoss" implTitle="JBoss EJB 3.0" implVendorID="http://www.jboss.org/" implURL="http://www.jboss.com/products/ejb3" sealed="false" md5Digest="6288cc8b99aa65940f6887e76a593221"/>
  <jar name="jboss-ejb3-interceptors.jar" specVersion="1.0.0-Beta3" specVendor="JBoss Inc." specTitle="JBoss EJB 3.0 Interceptors" implVersion="1.0.0-Beta3" implVendor="JBoss Inc." implTitle="JBoss EJB 3.0 Interceptors" implVendorID="org.jboss.ejb3" implURL="http://www.jboss.org" sealed="false" md5Digest="78782d30ab6d65c49b8c5c1617802043"/>
  <jar name="jboss-ejb3-metadata.jar" specVersion="0.13.0" specVendor="JBoss Inc." specTitle="JBoss EJB 3.0 Meta Data bridge" implVersion="0.13.0" implVendor="JBoss Inc." implTitle="JBoss EJB 3.0 Meta Data bridge" implVendorID="org.jboss.ejb3" implURL="http://www.jboss.org" sealed="false" md5Digest="f69e5924cc6f4b81a3a8eee76ccc73f"/>
  <jar name="jboss-ejb3-proxy-client.jar" specVersion="5.0.0.GA" specVendor="JBoss (http://www.jboss.org/)" specTitle="JBoss" implVersion="5.0.0.GA (build: SVNTag=JBoss_5_0_0_GA date=200812041714)" implVendor="JBoss Inc." implTitle="JBoss [Morpheus]" implVendorID="http://www.jboss.org/" implURL="http://www.jboss.org/" sealed="false" md5Digest="5d1dd8463898aeb227241f63b994953e"/>
  <jar name="jboss-ejb3-proxy-clustered-client.jar" specVersion="5.0.0.GA" specVendor="JBoss (http://www.jboss.org/)" specTitle="JBoss" implVersion="5.0.0.GA (build: SVNTag=JBoss_5_0_0_GA date=200812041714)" implVendor="JBoss Inc." implTitle="JBoss [Morpheus]" implVendorID="http://www.jboss.org/" implURL="http://www.jboss.org/" sealed="false" md5Digest="da353b2319ddb43fb7bf1e4bcf04ac4a"/>
  <jar name="jboss-ejb3-proxy-clustered.jar" specVersion="1.0.0-Beta3" specVendor="JBoss Inc." specTitle="JBoss EJB 3.0 Clustered Proxy" implVersion="1.0.0-Beta3" implVendor="JBoss Inc." implTitle="JBoss EJB 3.0 Clustered Proxy" implVendorID="org.jboss.ejb3" implURL="http://www.jboss.org/jbossejb3" sealed="false" md5Digest="e1b52ab4a0b462c385c3f4c5bcf30c2"/>
  <jar name="jboss-ejb3-proxy.jar" specVersion="1.0.0-Beta5" specVendor="JBoss Inc." specTitle="JBoss EJB 3.0 Proxy" implVersion="1.0.0-Beta5" implVendor="JBoss Inc." implTitle="JBoss EJB 3.0 Proxy" implVendorID="org.jboss.ejb3" implURL="http://www.jboss.org/jbossejb3" sealed="false" md5Digest="a6247aeaddfd819cd7c3baedf24490c8"/>
  <jar name="jboss-ejb3-security-client.jar" specVersion="5.0.0.GA" specVendor="JBoss (http://www.jboss.org/)" specTitle="JBoss" implVersion="5.0.0.GA (build: SVNTag=JBoss_5_0_0_GA date=200812041714)" implVendor="JBoss Inc." implTitle="JBoss [Morpheus]" implVendorID="http://www.jboss.org/" implURL="http://www.jboss.org/" sealed="false" md5Digest="54bdac0baf9c652258af5d0f008065bd"/>
  <jar name="jboss-ejb3-security.jar" specVersion="1.0.0-Beta2" specVendor="JBoss Inc." specTitle="JBoss EJB 3.0 Security" implVersion="1.0.0-Beta2" implVendor="JBoss Inc." implTitle="JBoss EJB 3.0 Security" implVendorID="org.jboss.ejb3" implURL="http://labs.jboss.com/jbossejb3/" sealed="false" md5Digest="f299e1f4d9ceb656aed36c6b3ebf9855"/>
  <jar name="jboss-ejb3-transactions.jar" specVersion="1.0.0-Beta1" specVendor="JBoss Inc." specTitle="JBoss EJB 3.0 Transactions" implVersion="1.0.0-Beta1" implVendor="JBoss Inc." implTitle="JBoss EJB 3.0 Transactions" implVendorID="org.jboss.ejb3" implURL="http://www.jboss.org" sealed="false" md5Digest="b8de04d132bcf5dc389d297f92934b65"/>
  <jar name="jboss-faces.jar" specVersion="5.0.0.GA" specVendor="JBoss (http://www.jboss.org/)" specTitle="JBoss" implVersion="5.0.0.GA (build: SVNTag=JBoss_5_0_0_GA date=200812041714)" implVendor="JBoss Inc." implTitle="JBoss [Morpheus]" implVendorID="http://www.jboss.org/" implURL="http://www.jboss.org/" sealed="false" md5Digest="6c1844140c758acca7a9620a342a038c"/>
  <jar name="jboss-ha-client.jar" specVersion="1.1.0.GA" specVendor="JBoss, a division of Red Hat, Inc." specTitle="JBoss Cluster HA Client Classes" implVersion="1.1.0.GA" implVendor="JBoss, a division of Red Hat, Inc." implTitle="JBoss Cluster HA Client Classes" implVendorID="org.jboss.cluster" implURL="http://www.jboss.org" sealed="false" md5Digest="965295776ef1a0548141303bcbfdce8a"/>
  <jar name="jboss-ha-legacy-client.jar" specVersion="5.0.0.GA" specVendor="JBoss (http://www.jboss.org/)" specTitle="JBoss" implVersion="5.0.0.GA (build: SVNTag=JBoss_5_0_0_GA date=200812041714)" implVendor="JBoss Inc." implTitle="JBoss [Morpheus]" implVendorID="http://www.jboss.org/" implURL="http://www.jboss.org/" sealed="false" md5Digest="66710758acb1a3dd96c84faf7562ce64"/>
  <jar name="jboss-ha-server-api.jar" specVersion="1.1.0.GA" specVendor="JBoss, a division of Red Hat, Inc." specTitle="JBoss Cluster HA Server API Classes" implVersion="1.1.0.GA" implVendor="JBoss, a division of Red Hat, Inc." implTitle="JBoss Cluster HA Server API Classes" implVendorID="org.jboss.cluster" implURL="http://www.jboss.org" sealed="false" md5Digest="a842078ae6b861f7404d37576e5c4f56"/>
  <jar name="jboss-ha-server-cache-jbc.jar" specVersion="1.1.0.GA" specVendor="JBoss, a division of Red Hat, Inc." specTitle="JBoss AS - JBoss Cache Integration Implementation" implVersion="1.1.0.GA" implVendor="JBoss, a division of Red Hat, Inc." implTitle="JBoss AS - JBoss Cache Integration Implementation" implVendorID="org.jboss.cluster" implURL="http://www.jboss.org" sealed="false" md5Digest="80191e426eab5272a2e7bc3e79db0d9a"/>
  <jar name="jboss-ha-server-cache-spi.jar" specVersion="1.1.0.GA" specVendor="JBoss, a division of Red Hat, Inc." specTitle="JBoss AS - JBoss Cache Integration SPI" implVersion="1.1.0.GA" implVendor="JBoss, a division of Red Hat, Inc." implTitle="JBoss AS - JBoss Cache Integration SPI" implVendorID="org.jboss.cluster" implURL="http://www.jboss.org" sealed="false" md5Digest="927a210738efcfdd2f236dabd22e23e5"/>
  <jar name="jboss-hibernate.jar" specVersion="5.0.0.GA" specVendor="JBoss (http://www.jboss.org/)" specTitle="JBoss" implVersion="5.0.0.GA (build: SVNTag=JBoss_5_0_0_GA date=200812041714)" implVendor="JBoss Inc." implTitle="JBoss [Morpheus]" implVendorID="http://www.jboss.org/" implURL="http://www.jboss.org/" sealed="false" md5Digest="25cc79ae3816477eb0f4b367b81d9e36"/>
  <jar name="jboss-iiop-client.jar" specVersion="5.0.0.GA" specVendor="JBoss (http://www.jboss.org/)" specTitle="JBoss" implVersion="5.0.0.GA (build: SVNTag=JBoss_5_0_0_GA date=200812041714)" implVendor="JBoss Inc." implTitle="JBoss [Morpheus]" implVendorID="http://www.jboss.org/" implURL="http://www.jboss.org/" sealed="false" md5Digest="33c2a5e82be5e6f9314b4c22a44ee4ce"/>
  <jar name="jboss-iiop.jar" specVersion="5.0.0.GA" specVendor="JBoss (http://www.jboss.org/)" specTitle="JBoss" implVersion="5.0.0.GA (build: SVNTag=JBoss_5_0_0_GA date=200812041714)" implVendor="JBoss Inc." implTitle="JBoss [Morpheus]" implVendorID="http://www.jboss.org/" implURL="http://www.jboss.org/" sealed="false" md5Digest="a7de9b58583024d812e78d9e70b996bb"/>
  <jar name="jboss-integration.jar" specVersion="5.0.0.GA" specVendor="JBoss (http://www.jboss.org/)" specTitle="JBoss" implVersion="5.0.0.GA (build: SVNTag=JBoss_5_0_0_GA date=200812041714)" implVendor="JBoss Inc." implTitle="JBoss [Morpheus]" implVendorID="http://www.jboss.org/" implURL="http://www.jboss.org/" sealed="false" md5Digest="3a9cdee664a462209c91f8a0bc235277"/>
  <jar name="jboss-j2se.jar" specVersion="5.0.0.GA" specVendor="JBoss (http://www.jboss.org/)" specTitle="JBoss" implVersion="5.0.0.GA (build: SVNTag=JBoss_5_0_0_GA date=200812041714)" implVendor="JBoss Inc." implTitle="JBoss [Morpheus]" implVendorID="http://www.jboss.org/" implURL="http://www.jboss.org/" sealed="false" md5Digest="f813c3411c4e8cae9c06e060adbc4fb6"/>
  <jar name="jboss-jaspi-api.jar" specVersion="1.0.0.GA" specVendor="JBoss Inc." specTitle="JBoss Java Authentication SPI for Containers 1.0-PR API" implVersion="1.0.0.GA" implVendor="JBoss Inc." implTitle="JBoss Java Authentication SPI for Containers 1.0-PR API" implVendorID="org.jboss.javaee" implURL="http://www.jboss.org" sealed="false" md5Digest="54adcfda4405c3e796e10a0692741c67"/>
  <jar name="jboss-javaee.jar" specVersion="5.0.0.GA" specVendor="JBoss (http://www.jboss.org/)" specTitle="JBoss" implVersion="5.0.0.GA (build: SVNTag=JBoss_5_0_0_GA date=200812041714)" implVendor="JBoss Inc." implTitle="JBoss [Morpheus]" implVendorID="http://www.jboss.org/" implURL="http://www.jboss.org/" sealed="false" md5Digest="9dba5286ea77e5b7f857362c8c079c15"/>
  <jar name="jboss-jaxb-intros.jar" specVersion="jboss-jaxbintros-1.0" specVendor="JBoss (http://www.jboss.org)" specTitle="JBossJAXBIntros" implVersion="jbossws-1.0.0.GA (build=200811102211)" implVendor="JBoss Inc." implTitle="JBoss JAXBIntros " implVendorID="http://www.jboss.org" implURL="http://www.jboss.org/products/jbossws" sealed="false" md5Digest="45cfbcbf9f20cdc3310e1294a8b83ced"/>
  <jar name="jboss-jca-deployer.jar" specVersion="5.0.0.GA" specVendor="JBoss (http://www.jboss.org/)" specTitle="JBoss" implVersion="5.0.0.GA (build: SVNTag=JBoss_5_0_0_GA date=200812041714)" implVendor="JBoss Inc." implTitle="JBoss [Morpheus]" implVendorID="http://www.jboss.org/" implURL="http://www.jboss.org/" sealed="false" md5Digest="71e48ffaf2084f97f6b31aee05f7fc71"/>
  <jar name="jboss-jca.jar" specVersion="5.0.0.GA" specVendor="JBoss (http://www.jboss.org/)" specTitle="JBoss" implVersion="5.0.0.GA (build: SVNTag=JBoss_5_0_0_GA date=200812041714)" implVendor="JBoss Inc." implTitle="JBoss [Morpheus]" implVendorID="http://www.jboss.org/" implURL="http://www.jboss.org/" sealed="false" md5Digest="32d9e4639c12c1f8c19b863ba67a9829"/>
  <jar name="jboss-jmx-remoting.jar" specVersion="5.0.0.GA" specVendor="JBoss (http://www.jboss.org/)" specTitle="JBoss" implVersion="5.0.0.GA (build: SVNTag=JBoss_5_0_0_GA date=200812041714)" implVendor="JBoss Inc." implTitle="JBoss [Morpheus]" implVendorID="http://www.jboss.org/" implURL="http://www.jboss.org/" sealed="false" md5Digest="c377211a89ec48c332ba610dad8e4c00"/>
  <jar name="jboss-jmx.jar" specVersion="5.0.0.GA" specVendor="JBoss (http://www.jboss.org/)" specTitle="JBoss" implVersion="5.0.0.GA (build: SVNTag=JBoss_5_0_0_GA date=200812041714)" implVendor="JBoss Inc." implTitle="JBoss [Morpheus]" implVendorID="http://www.jboss.org/" implURL="http://www.jboss.org/" sealed="false" md5Digest="5b6fa3329e8085f22581cd994a29719d"/>
  <jar name="jboss-jpa-deployers.jar" specVersion="1.0.0-Beta4" specVendor="JBoss, a division of Red Hat, Inc." specTitle="JBoss Container Managed JPA Deployers" implVersion="1.0.0-Beta4" implVendor="JBoss, a division of Red Hat, Inc." implTitle="JBoss Container Managed JPA Deployers" implVendorID="org.jboss.jpa" implURL="http://www.jboss.org/jboss-jpa-build/jboss-jpa-deployers" sealed="false" md5Digest="5f1b2a1ca9101754750e2def065a53b5"/>
  <jar name="jboss-jsr77-client.jar" specVersion="5.0.0.GA" specVendor="JBoss (http://www.jboss.org/)" specTitle="JBoss" implVersion="5.0.0.GA (build: SVNTag=JBoss_5_0_0_GA date=200812041714)" implVendor="JBoss Inc." implTitle="JBoss [Morpheus]" implVendorID="http://www.jboss.org/" implURL="http://www.jboss.org/" sealed="false" md5Digest="4ce706e7127f991f1bc09cdbb91e6575"/>
  <jar name="jboss-jsr77.jar" specVersion="5.0.0.GA" specVendor="JBoss (http://www.jboss.org/)" specTitle="JBoss" implVersion="5.0.0.GA (build: SVNTag=JBoss_5_0_0_GA date=200812041714)" implVendor="JBoss Inc." implTitle="JBoss [Morpheus]" implVendorID="http://www.jboss.org/" implURL="http://www.jboss.org/" sealed="false" md5Digest="8c8a7fa434226bdf506537d3d34ea9bc"/>
  <jar name="jboss-jsr88.jar" specVersion="5.0.0.GA" specVendor="JBoss (http://www.jboss.org/)" specTitle="JBoss" implVersion="5.0.0.GA (build: SVNTag=JBoss_5_0_0_GA date=200812041714)" implVendor="JBoss Inc." implTitle="JBoss [Morpheus]" implVendorID="http://www.jboss.org/" implURL="http://www.jboss.org/" sealed="false" md5Digest="cbe89c57275bedeadb5141f02ad4a08b"/>
  <jar name="jboss-kernel.jar" specVersion="2.0.2.GA" specVendor="JBoss, a division of Red Hat, Inc." specTitle="JBoss Microcontainer Kernel" implVersion="2.0.2.GA" implVendor="JBoss, a division of Red Hat, Inc." implTitle="JBoss Microcontainer Kernel" implVendorID="org.jboss.microcontainer" implURL="http://www.jboss.com/products/jbossmc" sealed="false" md5Digest="1fae08e1a796cf18cb157579f2d0b4af"/>
  <jar name="jboss-local-jdbc.rar" specVersion="5.0.0.GA" specVendor="JBoss (http://www.jboss.org/)" specTitle="JBoss" implVersion="5.0.0.GA (build: SVNTag=JBoss_5_0_0_GA date=200812041714)" implVendor="JBoss Inc." implTitle="JBoss [Morpheus]" implVendorID="http://www.jboss.org/" implURL="http://www.jboss.org/" sealed="false" md5Digest="62769fb46d26ec6ae472ad03a415b0f4"/>
  <jar name="jboss-logging-jdk.jar" specVersion="2.0.5.GA" specVendor="JBoss Inc." specTitle="JBoss Logging JDK" implVersion="2.0.5.GA" implVendor="JBoss Inc." implTitle="JBoss Logging JDK" implVendorID="org.jboss.logging" implURL="http://www.jboss.org" sealed="false" md5Digest="cbfade8d562351bb3d2988f47b6c2b87"/>
  <jar name="jboss-logging-log4j.jar" specVersion="2.0.5.GA" specVendor="JBoss Inc." specTitle="JBoss Logging Log4j" implVersion="2.0.5.GA" implVendor="JBoss Inc." implTitle="JBoss Logging Log4j" implVendorID="org.jboss.logging" implURL="http://www.jboss.org" sealed="false" md5Digest="ec6b5786828ee74e51b505ff3c93c737"/>
  <jar name="jboss-logging-spi.jar" specVersion="2.0.5.GA" specVendor="JBoss Inc." specTitle="JBoss Logging Programming Interface" implVersion="2.0.5.GA" implVendor="JBoss Inc." implTitle="JBoss Logging Programming Interface" implVendorID="org.jboss.logging" implURL="http://www.jboss.org" sealed="false" md5Digest="1193be516a21faa10bdc8ef95307f9b"/>
  <jar name="jboss-main-client.jar" specVersion="5.0.0.GA" specVendor="JBoss (http://www.jboss.org/)" specTitle="JBoss" implVersion="5.0.0.GA (build: SVNTag=JBoss_5_0_0_GA date=200812041714)" implVendor="JBoss Inc." implTitle="JBoss [Morpheus]" implVendorID="http://www.jboss.org/" implURL="http://www.jboss.org/" sealed="false" md5Digest="7806e0572cffde87025301d139eca3d8"/>
  <jar name="jboss-main.jar" specVersion="5.0.0.GA" specVendor="JBoss (http://www.jboss.org/)" specTitle="JBoss" implVersion="5.0.0.GA (build: SVNTag=JBoss_5_0_0_GA date=200812041714)" implVendor="JBoss Inc." implTitle="JBoss [Morpheus]" implVendorID="http://www.jboss.org/" implURL="http://www.jboss.org/" sealed="false" md5Digest="b10a8905552b4a2faf2bb411c7822136"/>
  <jar name="jboss-managed.jar" specVersion="2.0.0.GA" specVendor="JBoss, a division of Red Hat, Inc." specTitle="JBoss Managed" implVersion="2.0.0.GA" implVendor="JBoss, a division of Red Hat, Inc." implTitle="JBoss Managed" implVendorID="org.jboss.man" implURL="http://www.jboss.com/products/jbossmc" sealed="false" md5Digest="89aeeca4dad48c5a4efea5783be8c346"/>
  <jar name="jboss-management.jar" specVersion="5.0.0.GA" specVendor="JBoss (http://www.jboss.org/)" specTitle="JBoss" implVersion="5.0.0.GA (build: SVNTag=JBoss_5_0_0_GA date=200812041714)" implVendor="JBoss Inc." implTitle="JBoss [Morpheus]" implVendorID="http://www.jboss.org/" implURL="http://www.jboss.org/" sealed="false" md5Digest="e2244cf72b6962cd49bbb655f8ccd342"/>
  <jar name="jboss-mbeans.jar" specVersion="5.0.0.GA" specVendor="JBoss (http://www.jboss.org/)" specTitle="JBoss" implVersion="5.0.0.GA (build: SVNTag=JBoss_5_0_0_GA date=200812041714)" implVendor="JBoss Inc." implTitle="JBoss [Morpheus]" implVendorID="http://www.jboss.org/" implURL="http://www.jboss.org/" sealed="false" md5Digest="cea12e2f163889f19dc1c2375aa497d"/>
  <jar name="jboss-mdr.jar" specVersion="2.0.1.GA" specVendor="JBoss, a division of Red Hat, Inc." specTitle="JBoss MetaData Repository" implVersion="2.0.1.GA" implVendor="JBoss, a division of Red Hat, Inc." implTitle="JBoss MetaData Repository" implVendorID="org.jboss" implURL="http://www.jboss.com/products/jbossmc" sealed="false" md5Digest="db9d64c9001de9a65b0c8d0c55688620"/>
  <jar name="jboss-messaging-client.jar" specVersion="5.0.0.GA" specVendor="JBoss (http://www.jboss.org/)" specTitle="JBoss" implVersion="5.0.0.GA (build: SVNTag=JBoss_5_0_0_GA date=200812041714)" implVendor="JBoss Inc." implTitle="JBoss [Morpheus]" implVendorID="http://www.jboss.org/" implURL="http://www.jboss.org/" sealed="false" md5Digest="f81465a31e06ff445bff3a36921b97ee"/>
  <jar name="jboss-messaging-int.jar" specVersion="5.0.0.GA" specVendor="JBoss (http://www.jboss.org/)" specTitle="JBoss" implVersion="5.0.0.GA (build: SVNTag=JBoss_5_0_0_GA date=200812041714)" implVendor="JBoss Inc." implTitle="JBoss [Morpheus]" implVendorID="http://www.jboss.org/" implURL="http://www.jboss.org/" sealed="false" md5Digest="eec86f0d728e497caa19b025b3033e1"/>
  <jar name="jboss-messaging.jar" specVersion="1.4.1.GA" specVendor="JBoss Inc. (http://www.jboss.org/)" specTitle="JBoss Messaging" implVersion="1.4.1.GA (build: CVSTag=JBossMessaging_1_4_1_GA date=200811251945)" implVendor="JBoss Inc. (http://www.jboss.org/)" implTitle="JBoss Messaging" implVendorID="http://www.jboss.org/" implURL="http://www.jboss.org/" sealed="false" md5Digest="25bc9999fbff4e52cbecc87a716e9b1c"/>
  <jar name="jboss-metadata.jar" specVersion="1.0.0.CR11" specVendor="JBoss, a division of Red Hat, Inc." specTitle="JBoss Metadata" implVersion="1.0.0.CR11" implVendor="JBoss, a division of Red Hat, Inc." implTitle="JBoss Metadata" implVendorID="org.jboss.metadata" implURL="http://www.jboss.org" sealed="false" md5Digest="f066ad57896a49d42b77dc27ccc1c786"/>
  <jar name="jboss-metatype.jar" specVersion="2.0.0.GA" specVendor="JBoss, a division of Red Hat, Inc." specTitle="JBoss Metatype" implVersion="2.0.0.GA" implVendor="JBoss, a division of Red Hat, Inc." implTitle="JBoss Metatype" implVendorID="org.jboss.man" implURL="http://www.jboss.com/products/jbossmc" sealed="false" md5Digest="5c4a7c7cc6d00a3f3754d38ec473760f"/>
  <jar name="jboss-minimal.jar" specVersion="5.0.0.GA" specVendor="JBoss (http://www.jboss.org/)" specTitle="JBoss" implVersion="5.0.0.GA (build: SVNTag=JBoss_5_0_0_GA date=200812041714)" implVendor="JBoss Inc." implTitle="JBoss [Morpheus]" implVendorID="http://www.jboss.org/" implURL="http://www.jboss.org/" sealed="false" md5Digest="c126f25186d15e1f65fb3c3be47a54a4"/>
  <jar name="jboss-monitoring.jar" specVersion="5.0.0.GA" specVendor="JBoss (http://www.jboss.org/)" specTitle="JBoss" implVersion="5.0.0.GA (build: SVNTag=JBoss_5_0_0_GA date=200812041714)" implVendor="JBoss Inc." implTitle="JBoss [Morpheus]" implVendorID="http://www.jboss.org/" implURL="http://www.jboss.org/" sealed="false" md5Digest="db7265fd24c951747f726ab42247bb16"/>
  <jar name="jboss-profileservice-spi.jar" specVersion="5.0.3.GA" specVendor="JBoss, a division of Red Hat, Inc." specTitle="JBoss ProfileService 5.0.0 SPI" implVersion="5.0.3.GA" implVendor="JBoss, a division of Red Hat, Inc." implTitle="JBoss ProfileService 5.0.0 SPI" implVendorID="org.jboss.integration" implURL="http://www.jboss.org" sealed="false" md5Digest="6becee8b982e652ceddb0014764dc244"/>
  <jar name="jboss-profileservice.jar" specVersion="5.0.0.GA" specVendor="JBoss (http://www.jboss.org/)" specTitle="JBoss" implVersion="5.0.0.GA (build: SVNTag=JBoss_5_0_0_GA date=200812041714)" implVendor="JBoss Inc." implTitle="JBoss [Morpheus]" implVendorID="http://www.jboss.org/" implURL="http://www.jboss.org/" sealed="false" md5Digest="e42833107340073ab060c46d3573222f"/>
  <jar name="jboss-reflect.jar" specVersion="2.0.2.GA" specVendor="JBoss, a division of Red Hat, Inc." specTitle="JBoss Reflection" implVersion="2.0.2.GA" implVendor="JBoss, a division of Red Hat, Inc." implTitle="JBoss Reflection" implVendorID="org.jboss" implURL="http://www.jboss.com/products/jbossmc" sealed="false" md5Digest="e1c66c145459d57a5e247a4965d89524"/>
  <jar name="jboss-remoting-aspects.jar" specVersion="1.0.1.GA" specVendor="JBoss Inc." specTitle="JBoss Remoting Aspects" implVersion="1.0.1.GA" implVendor="JBoss Inc." implTitle="JBoss Remoting Aspects" implVendorID="org.jboss.aspects" implURL="http://www.jboss.org/jbossas" sealed="false" md5Digest="c2a44f7368d3bcd80cd532e10554de76"/>
  <jar name="jboss-remoting.jar" specVersion="5.0.0.GA" specVendor="JBoss (http://www.jboss.org/)" specTitle="JBoss" implVersion="5.0.0.GA (build: SVNTag=JBoss_5_0_0_GA date=200812041714)" implVendor="JBoss Inc." implTitle="JBoss [Morpheus]" implVendorID="http://www.jboss.org/" implURL="http://www.jboss.org/" sealed="false" md5Digest="7ac43ac794c4113ee90f37e0c06f0112"/>
  <jar name="jboss-seam-int-jbossas.jar" specVersion="5.0.0.GA" specVendor="JBoss, a division of Red Hat, Inc." specTitle="JBoss Seam Int JBossAS" implVersion="5.0.0.GA" implVendor="JBoss, a division of Red Hat, Inc." implTitle="JBoss Seam Int JBossAS" implVendorID="org.jboss.seam.integration" implURL="http://www.jboss.org/jbossmc/jboss-seam-int-jbossas" sealed="false" md5Digest="711f98f74fd0a4ab524ddcce548e9ce6"/>
  <jar name="jboss-seam-int-microcontainer.jar" specVersion="5.0.0.GA" specVendor="JBoss, a division of Red Hat, Inc." specTitle="JBoss Seam Int Microcontainer" implVersion="5.0.0.GA" implVendor="JBoss, a division of Red Hat, Inc." implTitle="JBoss Seam Int Microcontainer" implVendorID="org.jboss.seam.integration" implURL="http://www.jboss.org/jbossmc/jboss-seam-int-microcontainer" sealed="false" md5Digest="9bce0d9038a01ca307a6a500fae34685"/>
  <jar name="jboss-security-aspects.jar" specVersion="1.0.0.GA" specVendor="JBoss Inc." specTitle="JBoss Security Aspects" implVersion="1.0.0.GA" implVendor="JBoss Inc." implTitle="JBoss Security Aspects" implVendorID="org.jboss.aspects" implURL="http://www.jboss.org/jbossas/" sealed="false" md5Digest="b9e58463e29cb4cf3715ea216bc39ee3"/>
  <jar name="jboss-security-spi.jar" specVersion="5.0.0.GA" specVendor="JBoss Inc." specTitle="JBoss Security is a cross cutting project that handles security for the JEMS projects" implVersion="2.0.2.SP3" implVendor="JBoss Inc." implTitle="jboss-security-spi" implVendorID="http://www.jboss.org/" implURL="http://www.jboss.org/" sealed="false" md5Digest="572d501f7ade96d9404edec2231ff9c2"/>
  <jar name="jboss-serialization.jar" specVersion="5.0.0.GA" specVendor="JBoss (http://www.jboss.org/)" specTitle="JBoss" implVersion="5.0.0.GA (build: SVNTag=JBoss_5_0_0_GA date=200812041714)" implVendor="JBoss Inc." implTitle="JBoss [Morpheus]" implVendorID="http://www.jboss.org/" implURL="http://www.jboss.org/" sealed="false" md5Digest="5f93430eca83312b4ba755732dc4400f"/>
  <jar name="jboss-srp-client.jar" specVersion="5.0.0.GA" specVendor="JBoss (http://www.jboss.org/)" specTitle="JBoss" implVersion="5.0.0.GA (build: SVNTag=JBoss_5_0_0_GA date=200812041714)" implVendor="JBoss Inc." implTitle="JBoss [Morpheus]" implVendorID="http://www.jboss.org/" implURL="http://www.jboss.org/" sealed="false" md5Digest="77eb1b59b299d6cf44870abb8e10e636"/>
  <jar name="jboss-srp.jar" specVersion="5.0.0.GA" specVendor="JBoss (http://www.jboss.org/)" specTitle="JBoss" implVersion="5.0.0.GA (build: SVNTag=JBoss_5_0_0_GA date=200812041714)" implVendor="JBoss Inc." implTitle="JBoss [Morpheus]" implVendorID="http://www.jboss.org/" implURL="http://www.jboss.org/" sealed="false" md5Digest="d1bae1aeee4672177b49bdba739bea21"/>
  <jar name="jboss-sunxacml.jar" specVersion="2.0.2.SP1" specVendor="JBoss, a division of Red Hat, Inc." specTitle="JBoss port of sunxacml" implVersion="2.0.2.SP1" implVendor="JBoss, a division of Red Hat, Inc." implTitle="JBoss port of sunxacml" implVendorID="org.jboss.security" implURL="http://www.jboss.org" sealed="false" md5Digest="8feee120aeff916e6f854f432a22bd5"/>
  <jar name="jboss-system-client.jar" specVersion="5.0.0.GA" specVendor="JBoss (http://www.jboss.org/)" specTitle="JBoss" implVersion="5.0.0.GA (build: SVNTag=JBoss_5_0_0_GA date=200812041714)" implVendor="JBoss Inc." implTitle="JBoss [Morpheus]" implVendorID="http://www.jboss.org/" implURL="http://www.jboss.org/" sealed="false" md5Digest="2893d65787391cda1069e3b8f41cda66"/>
  <jar name="jboss-system-jmx-client.jar" specVersion="5.0.0.GA" specVendor="JBoss (http://www.jboss.org/)" specTitle="JBoss" implVersion="5.0.0.GA (build: SVNTag=JBoss_5_0_0_GA date=200812041714)" implVendor="JBoss Inc." implTitle="JBoss [Morpheus]" implVendorID="http://www.jboss.org/" implURL="http://www.jboss.org/" sealed="false" md5Digest="f62028d279f0d0865ed3f42bbdc30b72"/>
  <jar name="jboss-system-jmx.jar" specVersion="5.0.0.GA" specVendor="JBoss (http://www.jboss.org/)" specTitle="JBoss" implVersion="5.0.0.GA (build: SVNTag=JBoss_5_0_0_GA date=200812041714)" implVendor="JBoss Inc." implTitle="JBoss [Morpheus]" implVendorID="http://www.jboss.org/" implURL="http://www.jboss.org/" sealed="false" md5Digest="6a856661b0ffacc79411a776da3eddd"/>
  <jar name="jboss-system.jar" specVersion="5.0.0.GA" specVendor="JBoss (http://www.jboss.org/)" specTitle="JBoss" implVersion="5.0.0.GA (build: SVNTag=JBoss_5_0_0_GA date=200812041714)" implVendor="JBoss Inc." implTitle="JBoss [Morpheus]" implVendorID="http://www.jboss.org/" implURL="http://www.jboss.org/" sealed="false" md5Digest="c24b6e9932dbfbf9393a8e602bf3d37f"/>
  <jar name="jboss-transaction-aspects.jar" specVersion="1.0.0.GA" specVendor="JBoss Inc." specTitle="JBoss Transaction Aspects" implVersion="1.0.0.GA" implVendor="JBoss Inc." implTitle="JBoss Transaction Aspects" implVendorID="org.jboss.aspects" implURL="http://www.jboss.org/jbossas/" sealed="false" md5Digest="650bd96f6f0d911234926632c1acc38"/>
  <jar name="jboss-vfs.jar" specVersion="2.0.0.GA" specVendor="JBoss, A division of Red Hat, Inc" specTitle="JBoss VFS" implVersion="2.0.0.GA" implVendor="JBoss, A division of Red Hat, Inc" implTitle="JBoss VFS" implVendorID="org.jboss" implURL="http://www.jboss.org" sealed="false" md5Digest="486f117cf8215bc659c132ad81bfc1ad"/>
  <jar name="jboss-web-deployer.jar" specVersion="5.0.0.GA" specVendor="JBoss (http://www.jboss.org/)" specTitle="JBoss" implVersion="5.0.0.GA (build: SVNTag=JBoss_5_0_0_GA date=200812041714)" implVendor="JBoss Inc." implTitle="JBoss [Morpheus]" implVendorID="http://www.jboss.org/" implURL="http://www.jboss.org/" sealed="false" md5Digest="4f7c3cc1363e98da88c2813c7bb19e49"/>
  <jar name="jboss-web-service.jar" specVersion="5.0.0.GA" specVendor="JBoss (http://www.jboss.org/)" specTitle="JBoss" implVersion="5.0.0.GA (build: SVNTag=JBoss_5_0_0_GA date=200812041714)" implVendor="JBoss Inc." implTitle="JBoss [Morpheus]" implVendorID="http://www.jboss.org/" implURL="http://www.jboss.org/" sealed="false" md5Digest="2811e54f9eac47b4a9cd49ff71dc31c9"/>
  <jar name="jboss-xa-jdbc.rar" specVersion="5.0.0.GA" specVendor="JBoss (http://www.jboss.org/)" specTitle="JBoss" implVersion="5.0.0.GA (build: SVNTag=JBoss_5_0_0_GA date=200812041714)" implVendor="JBoss Inc." implTitle="JBoss [Morpheus]" implVendorID="http://www.jboss.org/" implURL="http://www.jboss.org/" sealed="false" md5Digest="9aa0aeace9a2c48b47d329ae1ebe9ff8"/>
  <jar name="jboss-xacml.jar" specVersion="2.0.2.SP1" specVendor="JBoss, a division of Red Hat, Inc." specTitle="JBoss XACML" implVersion="2.0.2.SP1" implVendor="JBoss, a division of Red Hat, Inc." implTitle="JBoss XACML" implVendorID="org.jboss.security" implURL="http://www.jboss.org" sealed="false" md5Digest="19c172a59e5ddcf90fc0bdde4e3b9fb4"/>
  <jar name="jboss-xml-binding.jar" specVersion="2.0.0.GA" specVendor="JBoss Inc." specTitle="JBoss XML Binding" implVersion="2.0.0.GA" implVendor="JBoss Inc." implTitle="JBoss XML Binding" implVendorID="org.jboss" implURL="http://www.jboss.org" sealed="false" md5Digest="9bd77605fde0d5231c1e2ab4f41a6482"/>
  <jar name="jboss.jar" specVersion="5.0.0.GA" specVendor="JBoss (http://www.jboss.org/)" specTitle="JBoss" implVersion="5.0.0.GA (build: SVNTag=JBoss_5_0_0_GA date=200812041714)" implVendor="JBoss Inc." implTitle="JBoss [Morpheus]" implVendorID="http://www.jboss.org/" implURL="http://www.jboss.org/" sealed="false" md5Digest="37ff4b4d40e01bac9aa1a38fc1509414"/>
  <jar name="jbossall-client.jar" specVersion="5.0.0.GA" specVendor="JBoss (http://www.jboss.org/)" specTitle="JBoss" implVersion="5.0.0.GA (build: SVNTag=JBoss_5_0_0_GA date=200812041714)" implVendor="JBoss Inc." implTitle="JBoss [Morpheus]" implVendorID="http://www.jboss.org/" implURL="http://www.jboss.org/" sealed="false" md5Digest="ef0987a9e4fb445bf29494c384782267"/>
  <jar name="jbossas-jmx-remoting.jar" specVersion="5.0.0.GA" specVendor="JBoss (http://www.jboss.org/)" specTitle="JBoss" implVersion="5.0.0.GA (build: SVNTag=JBoss_5_0_0_GA date=200812041714)" implVendor="JBoss Inc." implTitle="JBoss [Morpheus]" implVendorID="http://www.jboss.org/" implURL="http://www.jboss.org/" sealed="false" md5Digest="bd78dd6ef37c54e10caefa495ac63b60"/>
  <jar name="jbossas-remoting.jar" specVersion="5.0.0.GA" specVendor="JBoss (http://www.jboss.org/)" specTitle="JBoss" implVersion="5.0.0.GA (build: SVNTag=JBoss_5_0_0_GA date=200812041714)" implVendor="JBoss Inc." implTitle="JBoss [Morpheus]" implVendorID="http://www.jboss.org/" implURL="http://www.jboss.org/" sealed="false" md5Digest="b74d322803d2f04260064d5450286874"/>
  <jar name="jbosscache-core.jar" specVersion="3.0.1.GA" specVendor="JBoss, a division of Red Hat" specTitle="JBoss Cache - Core Edition" implVersion="3.0.1.GA" implVendor="JBoss, a division of Red Hat" implTitle="JBoss Cache - Core Edition" implVendorID="org.jboss.cache" implURL="http://www.jboss.org/" sealed="false" md5Digest="b1edf123b3699f443125a6c6bf5c3296"/>
  <jar name="jbosscache-pojo.jar" specVersion="3.0.0.GA" specVendor="JBoss, a division of Red Hat" specTitle="JBoss Cache - POJO Edition" implVersion="3.0.0.GA" implVendor="JBoss, a division of Red Hat" implTitle="JBoss Cache - POJO Edition" implVendorID="org.jboss.cache" implURL="http://www.jboss.org/" sealed="false" md5Digest="a35b298f28a67bc141a675187e875ea4"/>
  <jar name="jbosscx-client.jar" specVersion="5.0.0.GA" specVendor="JBoss (http://www.jboss.org/)" specTitle="JBoss" implVersion="5.0.0.GA (build: SVNTag=JBoss_5_0_0_GA date=200812041714)" implVendor="JBoss Inc." implTitle="JBoss [Morpheus]" implVendorID="http://www.jboss.org/" implURL="http://www.jboss.org/" sealed="false" md5Digest="60e4ec5dda233d87e94aef33bd73a5bd"/>
  <jar name="jbossha.jar" specVersion="5.0.0.GA" specVendor="JBoss (http://www.jboss.org/)" specTitle="JBoss" implVersion="5.0.0.GA (build: SVNTag=JBoss_5_0_0_GA date=200812041714)" implVendor="JBoss Inc." implTitle="JBoss [Morpheus]" implVendorID="http://www.jboss.org/" implURL="http://www.jboss.org/" sealed="false" md5Digest="54c34714d681e5633e7a7e1a924fbd5"/>
  <jar name="jbossjmx-ant.jar" specVersion="5.0.0.GA" specVendor="JBoss (http://www.jboss.org/)" specTitle="JBoss" implVersion="5.0.0.GA (build: SVNTag=JBoss_5_0_0_GA date=200812041714)" implVendor="JBoss Inc." implTitle="JBoss [Morpheus]" implVendorID="http://www.jboss.org/" implURL="http://www.jboss.org/" sealed="false" md5Digest="5e4cb7c102113ff61c4b1dc61ca1d027"/>
  <jar name="jbossjta-integration.jar" specVersion="5.0.0.GA" specVendor="JBoss (http://www.jboss.org/)" specTitle="JBoss" implVersion="5.0.0.GA (build: SVNTag=JBoss_5_0_0_GA date=200812041714)" implVendor="JBoss Inc." implTitle="JBoss [Morpheus]" implVendorID="http://www.jboss.org/" implURL="http://www.jboss.org/" sealed="false" md5Digest="8791376f4287f2ecfab84193829aa1f7"/>
  <jar name="jbossjta.jar" specVersion="5.0.0.GA" specVendor="JBoss (http://www.jboss.org/)" specTitle="JBoss" implVersion="5.0.0.GA (build: SVNTag=JBoss_5_0_0_GA date=200812041714)" implVendor="JBoss Inc." implTitle="JBoss [Morpheus]" implVendorID="http://www.jboss.org/" implURL="http://www.jboss.org/" sealed="false" md5Digest="6b71173d48bd5971c054886fd4423602"/>
  <jar name="jbossjts-integration.jar" specVersion="5.0.0.GA" specVendor="JBoss (http://www.jboss.org/)" specTitle="JBoss" implVersion="5.0.0.GA (build: SVNTag=JBoss_5_0_0_GA date=200812041714)" implVendor="JBoss Inc." implTitle="JBoss [Morpheus]" implVendorID="http://www.jboss.org/" implURL="http://www.jboss.org/" sealed="false" md5Digest="40eb30db732c638491088d952e90e2b"/>
  <jar name="jbossjts-jacorb.jar" specVersion="5.0.0.GA" specVendor="JBoss (http://www.jboss.org/)" specTitle="JBoss" implVersion="5.0.0.GA (build: SVNTag=JBoss_5_0_0_GA date=200812041714)" implVendor="JBoss Inc." implTitle="JBoss [Morpheus]" implVendorID="http://www.jboss.org/" implURL="http://www.jboss.org/" sealed="false" md5Digest="95881ee0b5f8be46ead7e1ff4b5d96e1"/>
  <jar name="jbossjts.jar" specVersion="5.0.0.GA" specVendor="JBoss (http://www.jboss.org/)" specTitle="JBoss" implVersion="5.0.0.GA (build: SVNTag=JBoss_5_0_0_GA date=200812041714)" implVendor="JBoss Inc." implTitle="JBoss [Morpheus]" implVendorID="http://www.jboss.org/" implURL="http://www.jboss.org/" sealed="false" md5Digest="dc2f40834142fee9a417d3f0ff7a1f78"/>
  <jar name="jbosssx-as-client.jar" specVersion="5.0.0.GA" specVendor="JBoss (http://www.jboss.org/)" specTitle="JBoss" implVersion="5.0.0.GA (build: SVNTag=JBoss_5_0_0_GA date=200812041714)" implVendor="JBoss Inc." implTitle="JBoss [Morpheus]" implVendorID="http://www.jboss.org/" implURL="http://www.jboss.org/" sealed="false" md5Digest="74b62d3d9c231f80008841d03a998253"/>
  <jar name="jbosssx-client.jar" specVersion="2.0.2.SP3" specVendor="JBoss Inc." specTitle="JBoss Security Client" implVersion="2.0.2.SP3" implVendor="JBoss Inc." implTitle="JBoss Security Client" implVendorID="org.jboss.security" implURL="http://www.jboss.org" sealed="false" md5Digest="c65cf75ecf6ed8b4383f4149f3f54cf8"/>
  <jar name="jbosssx-server.jar" specVersion="5.0.0.GA" specVendor="JBoss (http://www.jboss.org/)" specTitle="JBoss" implVersion="5.0.0.GA (build: SVNTag=JBoss_5_0_0_GA date=200812041714)" implVendor="JBoss Inc." implTitle="JBoss [Morpheus]" implVendorID="http://www.jboss.org/" implURL="http://www.jboss.org/" sealed="false" md5Digest="7d935c7e9260fac7edf749b6a3e4ab1"/>
  <jar name="jbosssx.jar" specVersion="5.0.0.GA" specVendor="JBoss Inc." specTitle="JBoss Security is a cross cutting project that handles security for the JEMS projects" implVersion="2.0.2.SP3" implVendor="JBoss Inc." implTitle="jbosssx" implVendorID="http://www.jboss.org/" implURL="http://www.jboss.org/" sealed="false" md5Digest="8b1991ccd4c3576740775a6613cd7b7d"/>
  <jar name="jbossts-common.jar" specVersion="5.0.0.GA" specVendor="JBoss (http://www.jboss.org/)" specTitle="JBoss" implVersion="5.0.0.GA (build: SVNTag=JBoss_5_0_0_GA date=200812041714)" implVendor="JBoss Inc." implTitle="JBoss [Morpheus]" implVendorID="http://www.jboss.org/" implURL="http://www.jboss.org/" sealed="false" md5Digest="384d6bf0a8570495f04d7ffb9375bbe7"/>
  <jar name="jbossts-tools.sar" specVersion="5.0.0.GA" specVendor="JBoss (http://www.jboss.org/)" specTitle="JBoss" implVersion="5.0.0.GA (build: SVNTag=JBoss_5_0_0_GA date=200812041714)" implVendor="JBoss Inc." implTitle="JBoss [Morpheus]" implVendorID="http://www.jboss.org/" implURL="http://www.jboss.org/" sealed="false" md5Digest="2a39c5a5ca90b6e6c31eee8d7ab382f6"/>
  <jar name="jbossweb-cluster.aop" specVersion="5.0.0.GA" specVendor="JBoss (http://www.jboss.org/)" specTitle="JBoss" implVersion="5.0.0.GA (build: SVNTag=JBoss_5_0_0_GA date=200812041714)" implVendor="JBoss Inc." implTitle="JBoss [Morpheus]" implVendorID="http://www.jboss.org/" implURL="http://www.jboss.org/" sealed="false" md5Digest="bfa9f810084de8b05a86f6ee8dd0708b"/>
  <jar name="jbossweb.jar" specVersion="5.0.0.GA" specVendor="JBoss (http://www.jboss.org/)" specTitle="JBoss" implVersion="5.0.0.GA (build: SVNTag=JBoss_5_0_0_GA date=200812041714)" implVendor="JBoss Inc." implTitle="JBoss [Morpheus]" implVendorID="http://www.jboss.org/" implURL="http://www.jboss.org/" sealed="false" md5Digest="79c8764b589275f9af31ec75cfd7dd3a"/>
  <jar name="jbossws-common.jar" specVersion="5.0.0.GA" specVendor="JBoss (http://www.jboss.org/)" specTitle="JBoss" implVersion="1.0.7.GA" implVendor="JBoss, a division of Red Hat" implTitle="JBoss Web Services - Common" implVendorID="org.jboss.ws" implURL="http://www.jboss.org/" sealed="false" md5Digest="cdc9bb98c7e5f4a1c3ff8de1042bc3cf"/>
  <jar name="jbossws-framework.jar" specVersion="5.0.0.GA" specVendor="JBoss (http://www.jboss.org/)" specTitle="JBoss" implVersion="3.0.4.GA" implVendor="JBoss, a division of Red Hat" implTitle="JBoss Web Services - Framework Parent" implVendorID="org.jboss.ws" implURL="http://www.jboss.org/" sealed="false" md5Digest="11c0811f6a0d0567b6eaf7dd01542456"/>
  <jar name="jbossws-jboss50.jar" specVersion="5.0.0.GA" specVendor="JBoss (http://www.jboss.org/)" specTitle="JBoss" implVersion="5.0.0.GA (build: SVNTag=JBoss_5_0_0_GA date=200812041714) (build=200812041722)" implVendor="JBoss Inc." implTitle="JBoss [Morpheus]" implVendorID="http://www.jboss.org/" implURL="http://www.jboss.org/" sealed="false" md5Digest="de7eea3789cda5ca36400df11ba48aaa"/>
  <jar name="jbossws-native-client.jar" specVersion="5.0.0.GA" specVendor="JBoss (http://www.jboss.org/)" specTitle="JBoss" implVersion="3.0.4.SP1" implVendor="JBoss, a division of Red Hat" implTitle="JBoss Web Services - Stack Native Client" implVendorID="org.jboss.ws.native" implURL="http://www.jboss.org/" sealed="false" md5Digest="5ed9dd8ac94afe5659f173defb2fa701"/>
  <jar name="jbossws-native-core.jar" specVersion="5.0.0.GA" specVendor="JBoss (http://www.jboss.org/)" specTitle="JBoss" implVersion="3.0.4.SP1" implVendor="JBoss, a division of Red Hat" implTitle="JBoss Web Services - Stack Native Core" implVendorID="org.jboss.ws.native" implURL="http://www.jboss.org/" sealed="false" md5Digest="866e580d6bb9e6b04df33d1c409e605d"/>
  <jar name="jbossws-native-jaxrpc.jar" specVersion="5.0.0.GA" specVendor="JBoss (http://www.jboss.org/)" specTitle="JBoss" implVersion="3.0.4.SP1" implVendor="JBoss, a division of Red Hat" implTitle="JBoss Web Services - Stack Native JAX-RPC" implVendorID="org.jboss.ws.native" implURL="http://www.jboss.org/" sealed="false" md5Digest="45486de86246eb248a9dc2a59bbdde24"/>
  <jar name="jbossws-native-jaxws-ext.jar" specVersion="5.0.0.GA" specVendor="JBoss (http://www.jboss.org/)" specTitle="JBoss" implVersion="3.0.4.SP1" implVendor="JBoss, a division of Red Hat" implTitle="JBoss Web Services - Stack Native JAX-WS Ext" implVendorID="org.jboss.ws.native" implURL="http://www.jboss.org/" sealed="false" md5Digest="307cc03bb3d22c9cc954230cf0a4997b"/>
  <jar name="jbossws-native-jaxws.jar" specVersion="5.0.0.GA" specVendor="JBoss (http://www.jboss.org/)" specTitle="JBoss" implVersion="3.0.4.SP1" implVendor="JBoss, a division of Red Hat" implTitle="JBoss Web Services - Stack Native JAX-WS" implVendorID="org.jboss.ws.native" implURL="http://www.jboss.org/" sealed="false" md5Digest="d28a2c3a337dad352d0a83229784b6cc"/>
  <jar name="jbossws-native-saaj.jar" specVersion="5.0.0.GA" specVendor="JBoss (http://www.jboss.org/)" specTitle="JBoss" implVersion="3.0.4.SP1" implVendor="JBoss, a division of Red Hat" implTitle="JBoss Web Services - Stack Native SAAJ" implVendorID="org.jboss.ws.native" implURL="http://www.jboss.org/" sealed="false" md5Digest="835c399e179c16e1c73a311eb96c619f"/>
  <jar name="jbossws-spi.jar" specVersion="5.0.0.GA" specVendor="JBoss (http://www.jboss.org/)" specTitle="JBoss" implVersion="1.0.6.GA" implVendor="JBoss, a division of Red Hat" implTitle="JBoss Web Services - SPI" implVendorID="org.jboss.ws" implURL="http://www.jboss.org/" sealed="false" md5Digest="e706344278b4254c4b2f0b515131b64"/>
  <jar name="jcommon.jar" specVersion="5.0.0.GA" specVendor="JFree.org" specTitle="JCommon is a free general purpose Java class library that is used in   several projects at www.jfree.org, including JFreeChart and   JFreeReport." implVersion="1.0.2" implVendor="JFree.org" implTitle="jcommon" implVendorID="http://www.jboss.org/" implURL="http://www.jboss.org/" sealed="false" md5Digest="5942040ba719bdb16c98e1a590aee52a"/>
  <jar name="jettison.jar" specVersion="5.0.0.GA" specVendor="JBoss (http://www.jboss.org/)" specTitle="JBoss" implVersion="5.0.0.GA (build: SVNTag=JBoss_5_0_0_GA date=200812041714)" implVendor="JBoss Inc." implTitle="JBoss [Morpheus]" implVendorID="http://www.jboss.org/" implURL="http://www.jboss.org/" sealed="false" md5Digest="7d1cb0c30702b251d2f7271787d3b48"/>
  <jar name="jfreechart.jar" specVersion="5.0.0.GA" specVendor="JFree.org" specTitle="JFreeChart is a class library, written in Java, for generating charts.   Utilising the Java2D APIs, it currently supports bar charts, pie charts,   line charts, XY-plots and time series plots." implVersion="1.0.2" implVendor="JFree.org" implTitle="jfreechart" implVendorID="http://www.jboss.org/" implURL="http://www.jboss.org/" sealed="false" md5Digest="c78640b3172edc5366a5ad7648d83479"/>
  <jar name="jgroups.jar" specVersion="5.0.0.GA" specVendor="JBoss (http://www.jboss.org/)" specTitle="JBoss" implVersion="2.6.7.GA" implVendor="JBoss Inc." implTitle="JBoss [Morpheus]" implVendorID="http://www.jboss.org/" implURL="http://www.jboss.org/" sealed="false" md5Digest="5d17cdcf303e7d3bded216d4e9763090"/>
  <jar name="jms-ra.rar" specVersion="5.0.0.GA" specVendor="JBoss (http://www.jboss.org/)" specTitle="JBoss" implVersion="5.0.0.GA (build: SVNTag=JBoss_5_0_0_GA date=200812041714)" implVendor="JBoss Inc." implTitle="JBoss [Morpheus]" implVendorID="http://www.jboss.org/" implURL="http://www.jboss.org/" sealed="false" md5Digest="4854305052f0f65b21319fc73b497e41"/>
  <jar name="jmx-adaptor-plugin.jar" specVersion="5.0.0.GA" specVendor="JBoss (http://www.jboss.org/)" specTitle="JBoss" implVersion="5.0.0.GA (build: SVNTag=JBoss_5_0_0_GA date=200812041714)" implVendor="JBoss Inc." implTitle="JBoss [Morpheus]" implVendorID="http://www.jboss.org/" implURL="http://www.jboss.org/" sealed="false" md5Digest="e1e418b81ae3ccbba331cbe14007ced7"/>
  <jar name="jmx-client.jar" specVersion="5.0.0.GA" specVendor="JBoss (http://www.jboss.org/)" specTitle="JBoss" implVersion="5.0.0.GA (build: SVNTag=JBoss_5_0_0_GA date=200812041714)" implVendor="JBoss Inc." implTitle="JBoss [Morpheus]" implVendorID="http://www.jboss.org/" implURL="http://www.jboss.org/" sealed="false" md5Digest="e27a1f167fac6db640aad769fa9fef48"/>
  <jar name="jmx-invoker-adaptor-client.jar" specVersion="5.0.0.GA" specVendor="JBoss (http://www.jboss.org/)" specTitle="JBoss" implVersion="5.0.0.GA (build: SVNTag=JBoss_5_0_0_GA date=200812041714)" implVendor="JBoss Inc." implTitle="JBoss [Morpheus]" implVendorID="http://www.jboss.org/" implURL="http://www.jboss.org/" sealed="false" md5Digest="1952517dbd5c7a94902e66c87d57c5ec"/>
  <jar name="jnp-client.jar" specVersion="@specification.version@" specVendor="@specification.vendor@" specTitle="@specification.title@" implVersion="@implementation.version@" implVendor="@implementation.vendor@" implTitle="@implementation.title@" implVendorID="@implementation.vendor.id@" implURL="@implementation.url@" sealed="false" md5Digest="c6abea89de4f1e234fd9a707f7074fb4"/>
  <jar name="jnpserver.jar" specVersion="5.0.0.SP1" specVendor="JBoss, a division of Red Hat, Inc." specTitle="JBoss Naming Server" implVersion="5.0.0.SP1" implVendor="JBoss, a division of Red Hat, Inc." implTitle="JBoss Naming Server" implVendorID="org.jboss.naming" implURL="http://www.jboss.org" sealed="false" md5Digest="e09a31bcc5eb9124a80f415d902482d7"/>
  <jar name="joesnmp.jar" specVersion="5.0.0.GA" specVendor="JBoss (http://www.jboss.org/)" specTitle="JBoss" implVersion="0.3.4" implVendor="joeSNMP" implTitle="JBoss [Morpheus]" implVendorID="http://www.jboss.org/" implURL="http://sourceforge.net/projects/joesnmp" sealed="false" md5Digest="413db63722760c7b9efaa326f79c7cd6"/>
  <jar name="jrockit-pluggable-instrumentor.jar" specVersion="2.0.0.SP1" specVendor="JBoss, a division of Red Hat, Inc." specTitle="JBoss AOP JRockit Pluggable Instrumentor" implVersion="2.0.0.SP1" implVendor="JBoss, a division of Red Hat, Inc." implTitle="JBoss AOP JRockit Pluggable Instrumentor" implVendorID="org.jboss.aop" implURL="http://www.jboss.org/jbossaop/jrockit-pluggable-instrumentor" sealed="false" md5Digest="65f6a8b0d73c839954c492457c991bdf"/>
  <jar name="jsf-api.jar" specVersion="1.2MR2" specVendor="JBoss (http://www.jboss.org/)" specTitle="JavaServer Faces" implVersion="1.2_10-b01-FCS" implVendor="Sun Microsystems, Inc." implTitle="Mojarra" implVendorID="com.sun" implURL="http://www.jboss.org/" sealed="false" md5Digest="941f05babec69044bc00a2a74d9133a2"/>
  <jar name="jsf-impl.jar" specVersion="1.2MR2" specVendor="JBoss (http://www.jboss.org/)" specTitle="JavaServer Faces" implVersion="1.2_10-b01-FCS" implVendor="Sun Microsystems, Inc." implTitle="Mojarra" implVendorID="com.sun" implURL="http://www.jboss.org/" sealed="false" md5Digest="9ac516aac8d4cf9b79fafe3412fcc68e"/>
  <jar name="jsp-api.jar" specVersion="5.0.0.GA" specVendor="JBoss (http://www.jboss.org/)" specTitle="JBoss" implVersion="5.0.0.GA (build: SVNTag=JBoss_5_0_0_GA date=200812041714)" implVendor="JBoss Inc." implTitle="JBoss [Morpheus]" implVendorID="http://www.jboss.org/" implURL="http://www.jboss.org/" sealed="false" md5Digest="135d07f87976ea4aa9e22cc8326808c4"/>
  <jar name="jstl.jar" specVersion="1.2" specVendor="Sun Microsystems, Inc." specTitle="JavaServer Pages(TM) Standard Tag Library" implVersion="1.2" implVendor="Sun Microsystems, Inc." implTitle="Sun Java System Application Server" implVendorID="org.apache" implURL="http://www.jboss.org/" sealed="false" md5Digest="1b97d2998e8084eb39a4ceb0163e3cac"/>
  <jar name="juddi-saaj.jar" specVersion="5.0.0.GA" specVendor="JBoss (http://www.jboss.org/)" specTitle="JBoss" implVersion="5.0.0.GA (build: SVNTag=JBoss_5_0_0_GA date=200812041714)" implVendor="JBoss Inc." implTitle="JBoss [Morpheus]" implVendorID="http://www.jboss.org/" implURL="http://www.jboss.org/" sealed="false" md5Digest="490e26cc9a68365fd0294b8eb5fcf119"/>
  <jar name="juddi-service.jar" specVersion="5.0.0.GA" specVendor="JBoss (http://www.jboss.org/)" specTitle="JBoss" implVersion="5.0.0.GA (build: SVNTag=JBoss_5_0_0_GA date=200812041714)" implVendor="JBoss Inc." implTitle="JBoss [Morpheus]" implVendorID="http://www.jboss.org/" implURL="http://www.jboss.org/" sealed="false" md5Digest="2794afdbb51baa6f038dc97ba025272f"/>
  <jar name="juddi.jar" specVersion="5.0.0.GA" specVendor="JBoss (http://www.jboss.org/)" specTitle="JBoss" implVersion="5.0.0.GA (build: SVNTag=JBoss_5_0_0_GA date=200812041714)" implVendor="JBoss Inc." implTitle="JBoss [Morpheus]" implVendorID="http://www.jboss.org/" implURL="http://www.jboss.org/" sealed="false" md5Digest="dad64d1d43e538db314320a181c93ac9"/>
  <jar name="log4j-boot.jar" specVersion="5.0.0.GA" specVendor="JBoss (http://www.jboss.org/)" specTitle="JBoss" implVersion="5.0.0.GA (build: SVNTag=JBoss_5_0_0_GA date=200812041714)" implVendor="JBoss Inc." implTitle="JBoss [Morpheus]" implVendorID="http://www.jboss.org/" implURL="http://www.jboss.org/" sealed="false" md5Digest="c1fae1b1d30b5bcb27a2aa3b23375715"/>
  <jar name="log4j-snmp-appender.jar" specVersion="5.0.0.GA" specVendor="JBoss (http://www.jboss.org/)" specTitle="JBoss" implVersion="5.0.0.GA (build: SVNTag=JBoss_5_0_0_GA date=200812041714)" implVendor="JBoss Inc." implTitle="JBoss [Morpheus]" implVendorID="http://www.jboss.org/" implURL="http://www.jboss.org/" sealed="false" md5Digest="c21c026bda29e66654900a63da3e50cc"/>
  <jar name="log4j.jar" specVersion="5.0.0.GA" specVendor="JBoss (http://www.jboss.org/)" specTitle="JBoss" implVersion="5.0.0.GA (build: SVNTag=JBoss_5_0_0_GA date=200812041714)" implVendor="JBoss Inc." implTitle="JBoss [Morpheus]" implVendorID="http://www.jboss.org/" implURL="http://www.jboss.org/" sealed="false" md5Digest="76b80f3b9d981735cee7c0374a70dceb"/>
  <jar name="logging-monitor.jar" specVersion="5.0.0.GA" specVendor="JBoss (http://www.jboss.org/)" specTitle="JBoss" implVersion="5.0.0.GA (build: SVNTag=JBoss_5_0_0_GA date=200812041714)" implVendor="JBoss Inc." implTitle="JBoss [Morpheus]" implVendorID="http://www.jboss.org/" implURL="http://www.jboss.org/" sealed="false" md5Digest="5ae277e4ae250ff345fb5b144e5ef4d1"/>
  <jar name="logkit.jar" specVersion="1.0" specVendor="Apache Software Foundation" specTitle="JBoss" implVersion="1.2" implVendor="Apache Software Foundation" implTitle="JBoss [Morpheus]" implVendorID="ASF" implURL="http://www.jboss.org/" sealed="false" md5Digest="8c94ac12779338b40fbc6056723381cd"/>
  <jar name="mail-plugin.jar" specVersion="5.0.0.GA" specVendor="JBoss (http://www.jboss.org/)" specTitle="JBoss" implVersion="5.0.0.GA (build: SVNTag=JBoss_5_0_0_GA date=200812041714)" implVendor="JBoss Inc." implTitle="JBoss [Morpheus]" implVendorID="http://www.jboss.org/" implURL="http://www.jboss.org/" sealed="false" md5Digest="2f21fc4784f9c715edae8fcd94224e73"/>
  <jar name="mail-ra.rar" specVersion="5.0.0.GA" specVendor="JBoss (http://www.jboss.org/)" specTitle="JBoss" implVersion="5.0.0.GA (build: SVNTag=JBoss_5_0_0_GA date=200812041714)" implVendor="JBoss Inc." implTitle="JBoss [Morpheus]" implVendorID="http://www.jboss.org/" implURL="http://www.jboss.org/" sealed="false" md5Digest="da617df7201f6245c943d7f53276f2ba"/>
  <jar name="mail.jar" specVersion="1.4" specVendor="Sun Microsystems, Inc." specTitle="JavaMail(TM) API Design Specification" implVersion="1.4" implVendor="Sun Microsystems, Inc." implTitle="JavaMail(TM) API Reference Implementation" implVendorID="com.sun" implURL="http://www.jboss.org/" sealed="false" md5Digest="55fa8ef589cbb6188c35c8d667d62e7c"/>
  <jar name="netboot.war" specVersion="5.0.0.GA" specVendor="JBoss (http://www.jboss.org/)" specTitle="JBoss" implVersion="5.0.0.GA (build: SVNTag=JBoss_5_0_0_GA date=200812041714)" implVendor="JBoss Inc." implTitle="JBoss [Morpheus]" implVendorID="http://www.jboss.org/" implURL="http://www.jboss.org/" sealed="false" md5Digest="c0b0bfc5b33c0574eeeef69461fc3e79"/>
  <jar name="osgi.core.jar" specVersion="5.0.0.GA" specVendor="JBoss (http://www.jboss.org/)" specTitle="JBoss" implVersion="5.0.0.GA (build: SVNTag=JBoss_5_0_0_GA date=200812041714)" implVendor="JBoss Inc." implTitle="JBoss [Morpheus]" implVendorID="http://www.jboss.org/" implURL="http://www.jboss.org/" sealed="false" md5Digest="7c60999da06268171583fc2f6e2452fe"/>
  <jar name="otherimages.jar" specVersion="5.0.0.GA" specVendor="JBoss (http://www.jboss.org/)" specTitle="JBoss" implVersion="5.0.0.GA (build: SVNTag=JBoss_5_0_0_GA date=200812041714)" implVendor="JBoss Inc." implTitle="JBoss [Morpheus]" implVendorID="http://www.jboss.org/" implURL="http://www.jboss.org/" sealed="false" md5Digest="e5b9d25d8249af69140da1ef1353bca3"/>
  <jar name="pluggable-instrumentor.jar" specVersion="2.0.0.SP1" specVendor="JBoss, a division of Red Hat, Inc." specTitle="JBoss AOP Pluggable Instrumentor" implVersion="2.0.0.SP1" implVendor="JBoss, a division of Red Hat, Inc." implTitle="JBoss AOP Pluggable Instrumentor" implVendorID="org.jboss.aop" implURL="http://www.jboss.org/jbossaop/pluggable-instrumentor" sealed="false" md5Digest="95fe2cd350d320c16124c0af855bb682"/>
  <jar name="policy.jar" specVersion="5.0.0.GA" specVendor="Apache Software Foundation" specTitle="" implVersion="1.0" implVendor="Apache Software Foundation" implTitle="org.apache.ws.policy" implVendorID="http://www.jboss.org/" implURL="http://www.jboss.org/" sealed="false" md5Digest="ee7e8b66c37071d3046be847dc048dae"/>
  <jar name="properties-plugin.jar" specVersion="5.0.0.GA" specVendor="JBoss (http://www.jboss.org/)" specTitle="JBoss" implVersion="5.0.0.GA (build: SVNTag=JBoss_5_0_0_GA date=200812041714)" implVendor="JBoss Inc." implTitle="JBoss [Morpheus]" implVendorID="http://www.jboss.org/" implURL="http://www.jboss.org/" sealed="false" md5Digest="23c54d677f6ac22777650b9c98d50404"/>
  <jar name="quartz-ra.rar" specVersion="5.0.0.GA" specVendor="JBoss (http://www.jboss.org/)" specTitle="JBoss" implVersion="5.0.0.GA (build: SVNTag=JBoss_5_0_0_GA date=200812041714)" implVendor="JBoss Inc." implTitle="JBoss [Morpheus]" implVendorID="http://www.jboss.org/" implURL="http://www.jboss.org/" sealed="false" md5Digest="5fa807e82789bc17932e4209714d5c6a"/>
  <jar name="quartz.jar" specVersion="5.0.0.GA" specVendor="JBoss (http://www.jboss.org/)" specTitle="JBoss" implVersion="1.5.2" implVendor="OpenSymphony" implTitle="Quartz Enterprise Job Scheduler ALL" implVendorID="http://www.jboss.org/" implURL="http://www.jboss.org/" sealed="false" md5Digest="bd60d69e8011573fa9e8ed543bb794f0"/>
  <jar name="resolver.jar" specVersion="5.0.0.GA" specVendor="JBoss (http://www.jboss.org/)" specTitle="JBoss" implVersion="5.0.0.GA (build: SVNTag=JBoss_5_0_0_GA date=200812041714)" implVendor="JBoss Inc." implTitle="JBoss [Morpheus]" implVendorID="http://www.jboss.org/" implURL="http://www.jboss.org/" sealed="false" md5Digest="b15ae504faef01b78819b648f7d526c8"/>
  <jar name="run.jar" specVersion="5.0.0.GA" specVendor="JBoss (http://www.jboss.org/)" specTitle="JBoss" implVersion="5.0.0.GA (build: SVNTag=JBoss_5_0_0_GA date=200812041714)" implVendor="JBoss Inc." implTitle="JBoss [Morpheus]" implVendorID="http://www.jboss.org/" implURL="http://www.jboss.org/" sealed="false" md5Digest="715c7aceb27dcf4a473643e589072a8"/>
  <jar name="scheduler-plugin-example.jar" specVersion="5.0.0.GA" specVendor="JBoss (http://www.jboss.org/)" specTitle="JBoss" implVersion="5.0.0.GA (build: SVNTag=JBoss_5_0_0_GA date=200812041714)" implVendor="JBoss Inc." implTitle="JBoss [Morpheus]" implVendorID="http://www.jboss.org/" implURL="http://www.jboss.org/" sealed="false" md5Digest="4e049630e0dc648426e31e115051374b"/>
  <jar name="scheduler-plugin.jar" specVersion="5.0.0.GA" specVendor="JBoss (http://www.jboss.org/)" specTitle="JBoss" implVersion="5.0.0.GA (build: SVNTag=JBoss_5_0_0_GA date=200812041714)" implVendor="JBoss Inc." implTitle="JBoss [Morpheus]" implVendorID="http://www.jboss.org/" implURL="http://www.jboss.org/" sealed="false" md5Digest="c73ce72cb3e02b7346c62aa5eaa76d"/>
  <jar name="scout.jar" specVersion="5.0.0.GA" specVendor="JBoss (http://www.jboss.org/)" specTitle="JBoss" implVersion="5.0.0.GA (build: SVNTag=JBoss_5_0_0_GA date=200812041714)" implVendor="JBoss Inc." implTitle="JBoss [Morpheus]" implVendorID="http://www.jboss.org/" implURL="http://www.jboss.org/" sealed="false" md5Digest="a74d6cf989f70ab0517e50bdd5388379"/>
  <jar name="serializer.jar" specVersion="5.0.0.GA" specVendor="JBoss (http://www.jboss.org/)" specTitle="JBoss" implVersion="5.0.0.GA (build: SVNTag=JBoss_5_0_0_GA date=200812041714)" implVendor="JBoss Inc." implTitle="JBoss [Morpheus]" implVendorID="http://www.jboss.org/" implURL="http://www.jboss.org/" sealed="false" md5Digest="fe6ddd837795b32e8c1fc4ca34f58876"/>
  <jar name="servlet-api.jar" specVersion="5.0.0.GA" specVendor="JBoss (http://www.jboss.org/)" specTitle="JBoss" implVersion="5.0.0.GA (build: SVNTag=JBoss_5_0_0_GA date=200812041714)" implVendor="JBoss Inc." implTitle="JBoss [Morpheus]" implVendorID="http://www.jboss.org/" implURL="http://www.jboss.org/" sealed="false" md5Digest="648ba76cb5d100317947200d31b67da2"/>
  <jar name="shutdown.jar" specVersion="5.0.0.GA" specVendor="JBoss (http://www.jboss.org/)" specTitle="JBoss" implVersion="5.0.0.GA (build: SVNTag=JBoss_5_0_0_GA date=200812041714)" implVendor="JBoss Inc." implTitle="JBoss [Morpheus]" implVendorID="http://www.jboss.org/" implURL="http://www.jboss.org/" sealed="false" md5Digest="22235263f806c6a61a9bab493b8e78d"/>
  <jar name="slf4j-api.jar" specVersion="5.0.0.GA" specVendor="JBoss (http://www.jboss.org/)" specTitle="JBoss" implVersion="1.5.0" implVendor="JBoss Inc." implTitle="slf4j-api" implVendorID="http://www.jboss.org/" implURL="http://www.jboss.org/" sealed="false" md5Digest="d0841573796aa6b6dcf311e7e8f07a95"/>
  <jar name="slf4j-jboss-logging.jar" specVersion="1.0.0.GA" specVendor="JBoss Inc." specTitle="slf4j to JBoss Logging Adapter" implVersion="1.0.0.GA" implVendor="JBoss Inc." implTitle="slf4j to JBoss Logging Adapter" implVendorID="org.jboss.slf4j" implURL="http://www.jboss.org" sealed="false" md5Digest="9ecec96970ac30d9259f450fc624b6be"/>
  <jar name="snmp-adaptor.jar" specVersion="5.0.0.GA" specVendor="JBoss (http://www.jboss.org/)" specTitle="JBoss" implVersion="5.0.0.GA (build: SVNTag=JBoss_5_0_0_GA date=200812041714)" implVendor="JBoss Inc." implTitle="JBoss [Morpheus]" implVendorID="http://www.jboss.org/" implURL="http://www.jboss.org/" sealed="false" md5Digest="bbfa67a09245f23c049f3ae3c9562884"/>
  <jar name="stax-api.jar" specVersion="1.0" specVendor="JCP-173" specTitle="StAX" implVersion="1.0" implVendor="JCP" implTitle="StAX 1.0 API" implVendorID="http://www.jboss.org/" implURL="http://www.jboss.org/" sealed="false" md5Digest="f3289e16feec57ba7620278316c988ae"/>
  <jar name="stax-ex.jar" specVersion="5.0.0.GA" specVendor="JBoss (http://www.jboss.org/)" specTitle="JBoss" implVersion="5.0.0.GA (build: SVNTag=JBoss_5_0_0_GA date=200812041714)" implVendor="JBoss Inc." implTitle="JBoss [Morpheus]" implVendorID="http://www.jboss.org/" implURL="http://www.jboss.org/" sealed="false" md5Digest="18d89433c2abf1d402541fb7d285478d"/>
  <jar name="streambuffer.jar" specVersion="5.0.0.GA" specVendor="JBoss (http://www.jboss.org/)" specTitle="JBoss" implVersion="0.7" implVendor="Sun Microsystems, Inc." implTitle="XML Stream Buffer Implementation " implVendorID="com.sun" implURL="http://www.jboss.org/" sealed="false" md5Digest="529b71b4156bcea4a063ecd9c43f6f55"/>
  <jar name="threaddump.war" specVersion="5.0.0.GA" specVendor="JBoss (http://www.jboss.org/)" specTitle="JBoss" implVersion="5.0.0.GA (build: SVNTag=JBoss_5_0_0_GA date=200812041714)" implVendor="JBoss Inc." implTitle="JBoss [Morpheus]" implVendorID="http://www.jboss.org/" implURL="http://www.jboss.org/" sealed="false" md5Digest="1a8ce154d25566988622351f7e6f35ee"/>
  <jar name="trove.jar" specVersion="5.0.0.GA" specVendor="JBoss (http://www.jboss.org/)" specTitle="JBoss" implVersion="1.0.2" implVendor="JBoss Inc." implTitle="GNU Trove for Java" implVendorID="http://www.jboss.org/" implURL="http://trove4j.sourceforge.net/" sealed="false" md5Digest="160dacc4e571228eb61e3e8e86bc3735"/>
  <jar name="twiddle.jar" specVersion="5.0.0.GA" specVendor="JBoss (http://www.jboss.org/)" specTitle="JBoss" implVersion="5.0.0.GA (build: SVNTag=JBoss_5_0_0_GA date=200812041714)" implVendor="JBoss Inc." implTitle="JBoss [Morpheus]" implVendorID="http://www.jboss.org/" implURL="http://www.jboss.org/" sealed="false" md5Digest="f09685dc060f95def547f24f67073140"/>
  <jar name="wsdl4j.jar" specVersion="1.2" specVendor="IBM (Java Community Process)" specTitle="JWSDL" implVersion="1.6" implVendor="IBM" implTitle="WSDL4J" implVendorID="http://www.jboss.org/" implURL="http://www.jboss.org/" sealed="false" md5Digest="8f55cee5d8b00529c26627041dbaf734"/>
  <jar name="wstx.jar" specVersion="1.0" specVendor="http://jcp.org/en/jsr/detail?id=173" specTitle="StAX 1.0 API" implVersion="3.2.6" implVendor="woodstox.codehaus.org" implTitle="WoodSToX XML-processor" implVendorID="http://www.jboss.org/" implURL="http://www.jboss.org/" sealed="false" md5Digest="fec655e5aa7cacddd1bf21ba28631185"/>
  <jar name="xalan.jar" specVersion="5.0.0.GA" specVendor="JBoss (http://www.jboss.org/)" specTitle="JBoss" implVersion="5.0.0.GA (build: SVNTag=JBoss_5_0_0_GA date=200812041714)" implVendor="JBoss Inc." implTitle="JBoss [Morpheus]" implVendorID="http://www.jboss.org/" implURL="http://www.jboss.org/" sealed="false" md5Digest="2b008030bf3cbff5b521ae52dd6ef9ec"/>
  <jar name="xercesImpl.jar" specVersion="5.0.0.GA" specVendor="JBoss (http://www.jboss.org/)" specTitle="JBoss" implVersion="5.0.0.GA (build: SVNTag=JBoss_5_0_0_GA date=200812041714)" implVendor="JBoss Inc." implTitle="JBoss [Morpheus]" implVendorID="http://www.jboss.org/" implURL="http://www.jboss.org/" sealed="false" md5Digest="65cc43f7a75cbc32104e574a5ef93075"/>
  <jar name="xmlsec.jar" specVersion="5.0.0.GA" specVendor="JBoss (http://www.jboss.org/)" specTitle="JBoss" implVersion="5.0.0.GA (build: SVNTag=JBoss_5_0_0_GA date=200812041714)" implVendor="JBoss Inc." implTitle="JBoss [Morpheus]" implVendorID="http://www.jboss.org/" implURL="http://www.jboss.org/" sealed="false" md5Digest="8dd45e5fcd32a6250887b055190ac51d"/>
</jar-versions>
